Workbook
Name _______________________xlnm.Print_Area_7: #REF!
Name ______________________xlnm.Print_Area_7: #REF!
Name ______________________xlnm.Print_Area_7: #REF!
Name ______________________xlnm.Print_Area_7: #REF!
Name _____________________xlnm.Print_Area_7: #REF!
Name _____________________xlnm.Print_Area_7: #REF!
Name _____________________xlnm.Print_Area_7: #REF!
Name ____________________xlnm.Print_Area_7: #REF!
Name ____________________xlnm.Print_Area_7: #REF!
Name ____________________xlnm.Print_Area_7: #REF!
Name ___________________xlnm.Print_Area_7: #REF!
Name ___________________xlnm.Print_Area_7: #REF!
Name ___________________xlnm.Print_Area_7: #REF!
Name __________________xlnm.Print_Area_7: #REF!
Name __________________xlnm.Print_Area_7: #REF!
Name __________________xlnm.Print_Area_7: #REF!
Name __________________xlnm.Print_Area_7: #REF!
Name __________________xlnm.Print_Area_7: #REF!
Name _________________xlnm.Print_Area_7: #REF!
Name _________________xlnm.Print_Area_7: #REF!
Name _________________xlnm.Print_Area_7: #REF!
Name _________________xlnm.Print_Area_7: #REF!
Name _________________xlnm.Print_Area_7: #REF!
Name ________________xlnm.Print_Area_7: #REF!
Name ________________xlnm.Print_Area_7: #REF!
Name _______________xlnm.Print_Area_7: #REF!
Name _______________xlnm.Print_Area_7: #REF!
Name _______________xlnm.Print_Area_7: #REF!
Name _______________xlnm.Print_Area_7: #REF!
Name ______________xlnm.Print_Area_7: #REF!
Name ______________xlnm.Print_Area_7: #REF!
Name ______________xlnm.Print_Area_7: #REF!
Name ______________xlnm.Print_Area_7: #REF!
Name ______________xlnm.Print_Area_7: #REF!
Name _____________xlnm.Print_Area_7: #REF!
Name _____________xlnm.Print_Area_7: #REF!
Name _____________xlnm.Print_Area_7: #REF!
Name _____________xlnm.Print_Area_7: #REF!
Name _____________xlnm.Print_Area_7: #REF!
Name ____________xlnm.Print_Area_7: #REF!
Name ____________xlnm.Print_Area_7: #REF!
Name ____________xlnm.Print_Area_7: #REF!
Name ____________xlnm.Print_Area_7: #REF!
Name ___________xlnm.Print_Area_7: #REF!
Name ___________xlnm.Print_Area_7: #REF!
Name ___________xlnm.Print_Area_7: #REF!
Name ___________xlnm.Print_Area_7: #REF!
Name __________xlnm.Print_Area_7: #REF!
Name __________xlnm.Print_Area_7: #REF!
Name __________xlnm.Print_Area_7: #REF!
Name __________xlnm.Print_Area_7: #REF!
Name _________xlnm.Print_Area_7: #REF!
Name _________xlnm.Print_Area_7: #REF!
Name _________xlnm.Print_Area_7: #REF!
Name _________xlnm.Print_Area_7: #REF!
Name _________xlnm.Print_Area_7: #REF!
Name ________xlnm.Print_Area_7: #REF!
Name ________xlnm.Print_Area_7: #REF!
Name ________xlnm.Print_Area_7: #REF!
Name ________xlnm.Print_Area_7: #REF!

Sheet Covering Letter 
F4: Jakarta, 10 Februari 2025
B5: No. | C5: : | D5: CS/0001/2025
B6: Perihal | C6: : | D6: Penawaran Harga Jasa Job Supply Maintenance
B7: Lampiran | C7: : | D7: 7 Lembar
B9: Kepada Yth;
B10: PT United Tractors Tbk
B11: Jl. Raya Bekasi KM 22
B12: Kec. Cakung, Kota Jakarta Timur
B13: Daerah Khusus Ibukota Jakarta 13910
B15: Up | C15: : | D15: Ibu Sara Kirsti Loebis
D16: Corporate Governance & Sustainability Division Head
B19: Dengan hormat,
B20: Sehubungan dengan adanya kebutuhan Penyedia Jasa Tenaga Kerja di perusahaan Bapak/Ibu, bersama ini kami sampaikan penawaran dari PT Mitra Bakti UT sebagai berikut:
B22: - Penyedia Jasa Tenaga Kerja (rincian terlampir)
B23: Rp | D23: =RECAP!E19 -> 561637600
B25: Note :
B26: 1. Harga belum termasuk PPN 11%
B27: 2. Lingkup pekerjaan & Tools terlampir dalam proposal ini
B28: 3. Harga tersebut sudah termasuk BPJS Kesehatan, BPJS Ketenagakerjaan (BPJS Jaminan Kecelakaan Kerja,
B29: BPJS Jaminan Kematian, BPJS Jaminan Hari Tua, BPJS Jaminan Pensiun), Kompensasi Kerja (PP no 35
B30: Tahun 2021), Tunjangan Hari Raya (THR), Alat Pelindung Diri (APD) dan Pakaian Kerja
B31: 4. Harga sudah termasuk biaya MCU, kelebihan biaya MCU ditagihkan sesuai aktual dengan Management Fee 5%
B32: 5. Perhitungan dan aturan lembur sesuai aturan disnaker
B33: 6. Lembur ditagihkan sesuai aktual dengan management fee 5%
B34: 7. Makan disediakan oleh User
B35: 8. Sertifikasi akan dilakukan oleh User
B36: 9. Training ditagihkan sesuai aktual dengan management fee 5%
... B49: Strategic Business & Sales Division Head

Sheet RECAP
K3: 89669600
B4: Lampiran 1 | K4: =E13-K3 -> -767357.14
B5: No. | C5: ='Covering Letter '!D5 -> CS/0001/2025
B7: BIAYA JASA JOB SUPPLY MAINTENANCE BUILDING TAHUN 2025
B8: NAMA | E8: : PT MITRA BAKTI UT
B9: AREA PELAYANAN | E9: : PT UNITED TRACTORS TBK
R10: MP | T10: VENDOR | U10: TOOLS | V10: SUB TOTAL
B11: 1 | C11: MECHANICAL ELECTRICAL | E11: =V11 -> 1.2348654e+08 | R11: ='SC MP'!F42+'SC MP'!G42 -> 108061400 | S11: =('SC MP'!L42+'SC MP'!M42)*(13/28) -> 8062600 | T11: 0 | U11: =TOOLS!J21+TOOLS!I83 -> 7362538.6 | V11: =SUM(R11:U11) -> 1.2348654e+08
B12: 2 | C12: MAINTENANCE AC | E12: =V12 -> 1.1935622e+08 | R12: ='SC MP'!H42+'SC MP'!I42 -> 99913600 | S12: =('SC MP'!L42+'SC MP'!M42)*(12/28) -> 7442400 | T12: 0 | U12: =TOOLS!J21+TOOLS!I143 -> 12000219 | V12: =SUM(R12:U12) -> 1.1935622e+08
B13: 3 | C13: IPAL | E13: =V13 -> 88902243 | K13: =E13*12 -> 1.0668269e+09 | R13: ='SC MP'!J42+'SC MP'!K42 -> 25513400 | S13: =('SC MP'!L42+'SC MP'!M42)*(3/28) -> 1860600 | T13: =VENDOR!I6 -> 60509232 | U13: =TOOLS!J21 -> 1019010.5 | V13: =SUM(R13:U13) -> 88902243
B14: 4 | C14: ME & CIVIL PPI CAKUNG | E14: =V14 -> 1.0314786e+08 | R14: ='SC MP'!N42+'SC MP'!O42 -> 99913600 | S14: 0 | T14: =('SC MP'!M44+'SC MP'!N44)*(13/28) -> 0 | U14: =TOOLS!J21+TOOLS!I161 -> 3234261.1 | V14: =SUM(R14:U14) -> 1.0314786e+08
B15: 5 | C15: CIVIL REPAIR MAINTENANCE | E15: =V15 -> 100000000 | R15: ='SC MP'!F46+'SC MP'!G46 -> 0 | S15: 0 | T15: 100000000 | U15: =('SC MP'!N45+'SC MP'!O45)*(13/28) -> 0 | V15: =SUM(R15:U15) -> 100000000
B16: SUB TOTAL | E16: =SUM(E11:H15) -> 5.3489286e+08 | R16: =SUM(R11:S15) -> 350767600 | T16: =SUM(T11:T15) -> 1.6050923e+08 | U16: =SUM(U11:U15) -> 23616030 | V16: =SUM(V11:V15) -> 5.3489286e+08
B17: MANAGEMENT FEE 5% | E17: =E16*5% -> 26744643 | R17: 26744643
B18: GRAND TOTAL | E18: =E16+E17 -> 5.6163751e+08
B19: PEMBULATAN | E19: =ROUNDUP(E18,-2) -> 561637600
B21: SCOPE OF JOB | L21: HARGA 2024 | M21: HARGA 2025 | N21: DEVIASI | O21: %
B22: No | C22: Equipment | D22: Item Check | E22: Jumlah | F22: Satuan | G22: Biaya Per Bulan | H22: Biaya Per Tahun | L22: 908003000 | M22: =E19 -> 561637600 | N22: =M22-L22 -> -346365400 | O22: =N22/L22 -> -0.38145843
B23: 1 | C23: =C11 -> MECHANICAL ELECTRICAL
B24: a | C24: Genset | L24: Simulasi + Lembur | U24: 561637600
C25: Gedung UT New Building (UTNB) | D25: - Daily Check Inspection - Running Test | E25: 5 | F25: unit | G25: =E11 -> 1.2348654e+08 | H25: =G25*12 -> 1.4818385e+09 | L25: HARGA 2024 | M25: HARGA 2025 | N25: DEVIASI | O25: %
C26: Gedung Employee Center (EC) | E26: 1 | F26: unit | L26: 908003000 | M26: =M22 -> 561637600 | N26: =M28-L26 -> -2.4261794e+08 | O26: =N26/L26 -> -0.26719949
C27: Gedung ITC | E27: 1 | F27: unit | M27: =3167*'SC MP'!F20 -> 1.0374746e+08
C28: Gedung UT HO-B | E28: =4-1 -> 3 | F28: unit | M28: =SUM(M26:M27) -> 6.6538506e+08
C29: Gedung UT Corpu | E29: 1 | F29: unit
C30: Gedung KMSI | E30: 1 | F30: unit
C31: Area Masjid | E31: 1 | F31: unit
C32: Workshop UTPE (ex UTR) | E32: 1 | F32: unit
C33: Portable | E33: 1 | F33: unit
B34: b | C34: Hydrant
C35: Gedung UT New Building (UTNB) | D35: - Daily Check Inspection - Running Test | E35: 3 | F35: unit
C36: Gedung Employee Center (EC) | E36: 3 | F36: unit
C37: Area Yard Marketing | E37: 3 | F37: unit
C38: Gedung UT Corpu | E38: 3 | F38: unit
C39: Area UT Jababeka | E39: 3 | F39: unit
B40: c | C40: Pump
C41: Gedung UT New Building (UTNB) | D41: - Daily Check Inspection - Monthly Check | E41: 31 | F41: unit
C42: Gedung Employee Center (EC) | E42: 9 | F42: unit
C43: Gedung UT School | E43: 2 | F43: unit
C44: Gedung UT Corpu | E44: 6 | F44: unit
C45: Area Yard Marketing | E45: 3 | F45: unit
B46: d | C46: Transformer
C47: Gedung UT New Building (UTNB) | D47: - Daily Check Inspection - Running Test | E47: 3 | F47: unit
C48: Gedung Employee Center (EC) | E48: 1 | F48: unit
C49: Gedung ITC | E49: 1 | F49: unit
C50: Gedung UT Corpu | E50: 1 | F50: unit
C51: Gedung KMSI | E51: 1 | F51: unit
C52: Area Masjid | E52: 1 | F52: unit
B53: e | C53: Panel Listrik
C54: Gedung UT New Building (UTNB) | D54: - Daily Check - Cleaning Panel - Thermal Imager | E54: 138 | F54: unit
C55: PPI Cakung (Non UTNB) | E55: 124 | F55: unit
C56: Area UT Jababeka | E56: 14 | F56: unit
C57: Area UT Sukapura | E57: 16 | F57: unit
B58: f | C58: Barrier Gate
C59: Barrier Gate Passenger | D59: - Daily Check | E59: 3 | F59: unit
C60: Barrier Gate Parking | E60: 10 | F60: unit
B61: g | C61: Penyalur Petir
C62: Gedung UT New Building (UTNB) | D62: - Grounding Test | E62: 18 | F62: unit
C63: Gedung UT Corpu | E63: 5 | F63: unit
B64: h | C64: Automatic Door
C65: Gedung UT New Building (UTNB) | D65: - Daily Check | E65: 1 | F65: unit
C66: Gedung UT HO-B | E66: 1 | F66: unit
B67: i | C67: Access Door
C68: Gedung UT New Building (UTNB) | D68: - Daily Check | E68: 1 | F68: ls
B69: j | C69: Telecommunication (PABX)
C70: PPI Cakung | D70: - Daily Check | E70: 1 | F70: ls
B71: k | C71: CCTV
C72: PPI Cakung (Non UTNB) | D72: - Daily Check - Preventive 1 Month | E72: 285 | F72: unit
C73: Area UT Jababeka
C74: Area UT Sukapura
B75: l | C75: Fire Alarm
C76: Gedung UT New Building (UTNB) | D76: - Daily Check | E76: 452 | F76: unit
C77: Gedung Employee Center (EC) | E77: 88 | F77: unit
C78: Gedung ITC | E78: 116 | F78: unit
C79: Gedung UT School | E79: 92 | F79: unit
C80: Gedung UT HO-B | E80: 200 | F80: unit
C81: Gedung UT Corpu | E81: 157 | F81: unit
C82: Gedung KMSI | E82: 59 | F82: unit
C83: Gedung Parkir | E83: 244 | F83: unit
C84: Gedung Kanitra | E84: 52 | F84: unit
C85: Gedung Yayasan | E85: 45 | F85: unit
B86: m | C86: Elevator
C87: Gedung UT New Building (UTNB) | D87: - Daily Check | E87: 13 | F87: unit
C88: Gedung Employee Center (EC) | E88: 2 | F88: unit
C89: Gedung ITC | E89: 1 | F89: unit
C90: Gedung UT Corpu | E90: 1 | F90: unit
C91: Gedung KMSI | E91: 1 | F91: unit
B92: n | C92: Escalator
C93: Gedung UT New Building (UTNB) | D93: - Daily Check | E93: 2 | F93: unit
C94: Gedung Ballroom | E94: 4 | F94: unit
B95: o | C95: Angkat - Angkut
C96: Gondola Tower | D96: - Weekly Check | E96: 1 | F96: unit
C97: Gondola Wing | E97: 1 | F97: unit
C98: Over Head Crane | D98: - Weekly Check | E98: 1 | F98: unit
B99: p | C99: Aerial Platform
C100: Houlette | D100: - Pre Use Check - Weekly Check | E100: 1 | F100: unit
C101: Scissor Lift | E101: 1 | F101: unit
C102: Boom Lift | E102: 1 | F102: unit
B103: q | C103: Gym Equipment
C104: Gedung UT New Building (UTNB) | D104: - Daily Check | E104: 3 | F104: unit
...

Sheet SC MP
B5: Lampiran 1
B6: No. | C6: ='Covering Letter '!D5 -> CS/0001/2025
B8: STRUKTUR BIAYA JASA TENAGA KERJA
B9: TAHUN 2025
B10: AREA DKI JAKARTA
B12: NO | C12: URAIAN | F12: ME & TELECOMMUNICATION | H12: AC | J12: IPAL | L12: ALL | N12: TIM 10 | P12: KETERANGAN
F13: SUPERVISOR | G13: CREW | H13: SUPERVISOR | I13: CREW | J13: SUPERVISOR | K13: CREW | L13: KOORDINATOR | M13: ADMIN | N13: SUPERVISOR | O13: CREW
B14: I | C14: FIXED COST | F14: =SUM(F15:F18) -> 6849685.8 | G14: =SUM(G15:G18) -> 6849685.8 | H14: =SUM(H15:H18) -> 6849685.8 | I14: =SUM(I15:I18) -> 6849685.8 | J14: =SUM(J15:J18) -> 6849685.8 | K14: =SUM(K15:K18) -> 6849685.8 | L14: =SUM(L15:L18) -> 6849685.8 | M14: =SUM(M15:M18) -> 6849685.8 | ... O14: =SUM(O15:O18) -> 6849685.8 | Q14: 42
B15: 1 | C15: Upah | F15: =5068000*106.5% -> 5397420 | G15: =5068000*106.5% -> 5397420 | H15: =5068000*106.5% -> 5397420 | I15: =5068000*106.5% -> 5397420 | J15: =5068000*106.5% -> 5397420 | K15: =5068000*106.5% -> 5397420 | L15: =5068000*106.5% -> 5397420 | M15: =5068000*106.5% -> 5397420 | ... O15: =5068000*106.5% -> 5397420 | P15: Upah Tenaga Kerja (UMK 2025) | Q15: =F15*$Q$14 -> 226691640
B16: 2 | C16: BPJS | E16: 0.1024 | F16: 552695.81 | G16: 552695.81 | H16: 552695.81 | I16: 552695.81 | J16: 552695.81 | K16: 552695.81 | L16: 552695.81 | M16: 552695.81 | N16: =E16*N15 -> 552695.81 | O16: =E16*O15 -> 552695.81 | P16: Mengikuti Regulasi Pemerintah (JHT, JKK, JK) | Q16: =F16*$Q$14 -> 23213224
B17: 3 | C17: THR | F17: 449785 | G17: 449785 | H17: 449785 | I17: 449785 | J17: 449785 | K17: 449785 | L17: 449785 | M17: 449785 | N17: =N15/12 -> 449785 | O17: =O15/12 -> 449785 | P17: Upah /12 | Q17: =F17*$Q$14 -> 18890970
B18: 4 | C18: Kompensasi Akhir Kontrak (UUCK) | F18: 449785 | G18: 449785 | H18: 449785 | I18: 449785 | J18: 449785 | K18: 449785 | L18: 449785 | M18: 449785 | N18: =N15/12 -> 449785 | O18: =O15/12 -> 449785 | P18: Upah /12 | Q18: =F18*$Q$14 -> 18890970
B19: II | C19: OVERTIME | F19: =F22 -> 0 | G19: =G22 -> 0 | H19: =H22 -> 0 | I19: =I22 -> 0 | J19: =J22 -> 0 | K19: =K22 -> 0 | L19: =L22 -> 0 | M19: =M22 -> 0 | ... O19: =O22 -> 0 | Q19: =F19*$Q$14 -> 0
B20: 1 | C20: TUL | F20: =SUM(F15/173)*105% -> 32758.908 | G20: =SUM(G15/173)*105% -> 32758.908 | H20: =SUM(H15/173)*105% -> 32758.908 | I20: =SUM(I15/173)*105% -> 32758.908 | J20: =SUM(J15/173)*105% -> 32758.908 | K20: =SUM(K15/173)*105% -> 32758.908 | L20: =SUM(L15/173)*105% -> 32758.908 | M20: =SUM(M15/173)*105% -> 32758.908 | ... O20: =SUM(O15/173)*105% -> 32758.908 | P20: Upah /173 | Q20: =F20*$Q$14 -> 1375874.1
B21: 2 | C21: Jam Lembur | F21: 0 | G21: 0 | H21: 0 | I21: 0 | J21: 0 | K21: 0 | L21: 0 | M21: 0 | N21: 0 | O21: 0 | P21: Sesuai Aktual Dilapangan | Q21: =F21*$Q$14 -> 0
B22: 3 | C22: Upah Lembur | F22: =F20*F21 -> 0 | G22: =G20*G21 -> 0 | H22: =H20*H21 -> 0 | I22: =I20*I21 -> 0 | J22: =J20*J21 -> 0 | K22: =K20*K21 -> 0 | L22: =L20*L21 -> 0 | M22: =M20*M21 -> 0 | P22: Ditagihkan Sesuai Aktual Dengan Management Fee 5% | Q22: =F22*$Q$14 -> 0
B23: III | C23: VARIABLE COST | F23: =SUM(F24:F31) -> 1765000 | G23: =SUM(G24:G31) -> 765000 | H23: =SUM(H24:H31) -> 1765000 | I23: =SUM(I24:I31) -> 765000 | J23: =SUM(J24:J31) -> 1765000 | K23: =SUM(K24:K31) -> 765000 | L23: =SUM(L24:L31) -> 1765000 | M23: =SUM(M24:M31) -> 765000 | ... O23: =SUM(O24:O31) -> 765000 | Q23: =F23*$Q$14 -> 74130000
B24: 1 | C24: Medical Checkup | F24: 60000 | G24: 60000 | H24: 60000 | I24: 60000 | J24: 60000 | K24: 60000 | L24: 60000 | M24: 60000 | N24: 60000 | O24: 60000 | P24: Kelebihan biaya MCU ditagihkan sesuai aktual | Q24: =F24*$Q$14 -> 2520000
B25: 2 | C25: Seragam | F25: 135000 | G25: 135000 | H25: 135000 | I25: 135000 | J25: 135000 | K25: 135000 | L25: 135000 | M25: 135000 | N25: 135000 | O25: 135000 | P25: 3 Pasang Per Tahun (Baju, Kaos & Celana) | Q25: =F25*$Q$14 -> 5670000
B26: 3 | C26: APD | F26: 70000 | G26: 70000 | H26: 70000 | I26: 70000 | J26: 70000 | K26: 70000 | L26: 70000 | M26: 70000 | N26: 70000 | O26: 70000 | P26: Helm & sepatu safety | Q26: =F26*$Q$14 -> 2940000
B27: 4 | C27: Uang Makan | F27: 0 | G27: 0 | H27: 0 | I27: 0 | J27: 0 | K27: 0 | L27: 0 | M27: 0 | N27: 0 | O27: 0 | P27: Disediakan oleh User | Q27: =F27*$Q$14 -> 0
B28: 5 | C28: Sertifikasi | F28: 0 | G28: 0 | H28: 0 | I28: 0 | J28: 0 | K28: 0 | L28: 0 | M28: 0 | N28: 0 | O28: 0 | P28: Dilakukan oleh User | Q28: =F28*$Q$14 -> 0
B29: 6 | C29: Training | F29: 0 | G29: 0 | H29: 0 | I29: 0 | J29: 0 | K29: 0 | L29: 0 | M29: 0 | N29: 0 | O29: 0 | P29: Ditagihkan Sesuai Aktual Dengan Management Fee 5% | Q29: =F29*$Q$14 -> 0
B30: 7 | C30: Tunjangan Jabatan | F30: 1000000 | H30: 1000000 | J30: 1000000 | L30: 1000000 | N30: 1000000 | Q30: =F30*$Q$14 -> 42000000
B31: 8 | C31: Overhead Expenses | F31: =SUM(F32:F35) -> 500000 | G31: =SUM(G32:G35) -> 500000 | H31: =SUM(H32:H35) -> 500000 | I31: =SUM(I32:I35) -> 500000 | J31: =SUM(J32:J35) -> 500000 | K31: =SUM(K32:K35) -> 500000 | L31: =SUM(L32:L35) -> 500000 | M31: =SUM(M32:M35) -> 500000 | ... O31: =SUM(O32:O35) -> 500000 | Q31: =F31*$Q$14 -> 21000000
C32: Biaya Sambung Rasa | F32: 155000 | G32: 155000 | H32: 155000 | I32: 155000 | J32: 155000 | K32: 155000 | L32: 155000 | M32: 155000 | N32: 155000 | O32: 155000 | Q32: =F32*$Q$14 -> 6510000
C33: Biaya Recruitment | F33: 50000 | G33: 50000 | H33: 50000 | I33: 50000 | J33: 50000 | K33: 50000 | L33: 50000 | M33: 50000 | N33: 50000 | O33: 50000 | Q33: =F33*$Q$14 -> 2100000
C34: Biaya Suka Duka | F34: 45000 | G34: 45000 | H34: 45000 | I34: 45000 | J34: 45000 | K34: 45000 | L34: 45000 | M34: 45000 | N34: 45000 | O34: 45000 | Q34: =F34*$Q$14 -> 1890000
C35: Biaya Operational Support | F35: 250000 | G35: 250000 | H35: 250000 | I35: 250000 | J35: 250000 | K35: 250000 | L35: 250000 | M35: 250000 | N35: 250000 | O35: 250000 | Q35: =F35*$Q$14 -> 10500000
C36: TOTAL I + II + III | F36: =F14+F19+F23 -> 8614685.8 | G36: =G14+G19+G23 -> 7614685.8 | H36: =H14+H19+H23 -> 8614685.8 | I36: =I14+I19+I23 -> 7614685.8 | J36: =J14+J19+J23 -> 8614685.8 | K36: =K14+K19+K23 -> 7614685.8 | L36: =L14+L19+L23 -> 8614685.8 | M36: =M14+M19+M23 -> 7614685.8 | ... O36: =O14+O19+O23 -> 7614685.8 | Q36: =F36*$Q$14 -> 3.618168e+08
C37: MANAGEMENT FEE | E37: 0.07 | F37: =F36*$E$37 -> 603028.01 | G37: =G36*$E$37 -> 533028.01 | H37: =H36*$E$37 -> 603028.01 | I37: =I36*$E$37 -> 533028.01 | J37: =J36*$E$37 -> 603028.01 | K37: =K36*$E$37 -> 533028.01 | L37: =L36*$E$37 -> 603028.01 | M37: =M36*$E$37 -> 533028.01 | ... O37: =O36*$E$37 -> 533028.01 | Q37: =F37*$Q$14 -> 25327176
C38: SUB TOTAL | F38: =F36+F37 -> 9217713.8 | G38: =G36+G37 -> 8147713.8 | H38: =H36+H37 -> 9217713.8 | I38: =I36+I37 -> 8147713.8 | J38: =J36+J37 -> 9217713.8 | K38: =K36+K37 -> 8147713.8 | L38: =L36+L37 -> 9217713.8 | M38: =M36+M37 -> 8147713.8 | ... O38: =O36+O37 -> 8147713.8 | Q38: =F38*$Q$14 -> 3.8714398e+08
C39: PEMBULATAN | F39: =ROUNDUP(F38,-2) -> 9217800 | G39: =ROUNDUP(G38,-2) -> 8147800 | H39: =ROUNDUP(H38,-2) -> 9217800 | I39: =ROUNDUP(I38,-2) -> 8147800 | J39: =ROUNDUP(J38,-2) -> 9217800 | K39: =ROUNDUP(K38,-2) -> 8147800 | L39: =ROUNDUP(L38,-2) -> 9217800 | M39: =ROUNDUP(M38,-2) -> 8147800 | ... O39: =ROUNDUP(O38,-2) -> 8147800 | Q39: =F39*$Q$14 -> 387147600
C41: JUMLAH MANPOWER | F41: 2 | G41: 11 | H41: 2 | I41: 10 | J41: 1 | K41: 2 | L41: 1 | M41: 1 | N41: 2 | O41: 10 | P41: =SUM(F41:O41)-4 -> 38
C42: TOTAL BIAYA MANPOWER | F42: =F39*F41 -> 18435600 | G42: =G39*G41 -> 89625800 | H42: =H39*H41 -> 18435600 | I42: =I39*I41 -> 81478000 | J42: =J39*J41 -> 9217800 | K42: =K39*K41 -> 16295600 | L42: =L39*L41 -> 9217800 | M42: =M39*M41 -> 8147800 | ... O42: =O39*O41 -> 81478000 | P42: =SUM(F42:O42) -> 350767600
I43: 8
B47: Hormat Kami, | P47: Menyetujui,
B48: ='Covering Letter '!B43 -> PT Mitra Bakti UT | P48: ='Covering Letter '!B10 -> PT United Tractors Tbk
B54: ='Covering Letter '!B48 -> Sandy Yudha S | P54: =RIGHT('Covering Letter '!D15,18) -> Sara Kirsti Loebis
B55: Strategic Business & Sales Division Head | P55: ='Covering Letter '!D16 -> Corporate Governance & Sustainability Division Head
I59: SC IPAL 2024 | J59: 89669600
I60: MP 2025 | J60: =J42+K42 -> 25513400
I61: JARWO 2024/ Bulan | J61: 9500000
E63: OH | F63: =F31*F41 -> 1000000 | G63: =G31*G41 -> 5500000 | H63: =H31*H41 -> 1000000 | I63: =I31*I41 -> 5000000 | J63: =J31*J41 -> 500000 | K63: =K31*K41 -> 1000000 | L63: =L31*L41 -> 500000 | M63: =M31*M41 -> 500000 | ... O63: =O31*O41 -> 5000000 | P63: =SUM(F63:O63) -> 21000000
E64: M fee | F64: =F37*F41 -> 1206056 | G64: =G37*G41 -> 5863308.1 | H64: =H37*H41 -> 1206056 | I64: =I37*I41 -> 5330280.1 | J64: =J37*J41 -> 603028.01 | K64: =K37*K41 -> 1066056 | L64: =L37*L41 -> 603028.01 | M64: =M37*M41 -> 533028.01 | ... O64: =O37*O41 -> 5330280.1 | P64: =SUM(F64:O64) -> 22947176 | Q64: 22947176
P65: =SUM(P63:P64) -> 43947176 | Q65: =P65/P42 -> 0.12528859
P66: =P42-P65 -> 3.0682042e+08
E68: MP
E69: BPJS
E70: THR
E71: UUCK

Sheet SERTIFIKASI
A1: SERTIFIKASI MANPOWER MAINTENANCE
A3: Position | B3: Scope | C3: Jenis Sertifikasi | D3: Biaya Sertifikasi | E3: Masa Berlaku | F3: Biaya/ Bulan
A4: Supervisor | B4: ME & Telcom | C4: Sertifikasi Ahli K3 Listrik | D4: 7000000 | E4: 3 Tahun | F4: =D4/36 -> 194444.44
C5: Sertifikasi TKPK 1 (Tenaga Kerja pada Ketinggian Tingkat 1) | D5: 7500000 | E5: 3 Tahun | F5: =D5/36 -> 208333.33 | G5: New
A6: Crew | B6: ME & Telcom | C6: Sertifikasi Ahli K3 Listrik | D6: 7000000 | E6: 3 Tahun | F6: =D6/36 -> 194444.44
A7: Supervisor | B7: AC | C7: Sertifikasi AC/HVAC | D7: 6500000 | E7: 3 Tahun | F7: =D7/36 -> 180555.56
C8: Sertifikasi TKPK 1 (Tenaga Kerja pada Ketinggian Tingkat 1) | D8: 7500000 | E8: 3 Tahun | F8: =D8/36 -> 208333.33 | G8: New
A9: Crew | B9: AC | C9: Sertifikasi Ahli K3 AC/HVAC | D9: 6500000 | E9: 3 Tahun | F9: =D9/36 -> 180555.56
A10: Supervisor | B10: IPAL | C10: Sertifikasi terkait keselamatan kerja dan pengelolaan instalasi air limbah. | D10: 6500000 | E10: 3 Tahun | F10: =D10/36 -> 180555.56
A11: Crew | B11: IPAL | C11: Sertifikasi terkait keselamatan kerja dan pengelolaan instalasi air limbah. | D11: 6500000 | E11: 3 Tahun | F11: =D11/36 -> 180555.56
A12: Koordinator | B12: ME & Telcom | C12: Sertifikasi Ahli K3 Listrik | D12: 7000000 | E12: 3 Tahun | F12: =D12/36 -> 194444.44

Sheet VENDOR
B1: Cost Vendor
B2: No | C2: Klasifikasi | D2: Activity | E2: Vendor | F2: Qty | G2: Satuan | H2: Unit Price | I2: Amount (Month) | J2: Amount (Year)
B4: 1 | C4: IPAL | D4: IPAL | E4: Jarwo | F4: 1 | G4: Unit | H4: 52492232 | I4: =F4*H4 -> 52492232 | J4: =I4*12 -> 6.2990679e+08
B5: 2 | C5: IPAL | D5: LAB | E5: PT Mitra Bakti UT | F5: 1 | G5: Ls | H5: 8017000 | I5: =F5*H5 -> 8017000 | J5: =I5*12 -> 96204000
H6: =SUM(H4:H5) -> 60509232 | I6: =SUM(I4:I5) -> 60509232 | J6: =SUM(J4:J5) -> 7.2611079e+08
G8: Cost 2025/ Year | H8: 1105264500
G9: SC IPAL 2024 | H9: 89669600
G10: MP 2025 | H10: 26228600
G11: Jarwo 2025 | H11: 35213750
G12: CS 2025 | H12: =RECAP!E13 -> 88902243
G13: Cost MP | H13: =RECAP!R13+RECAP!S13 -> 27374000
G14: Cost Tools | H14: =RECAP!U13 -> 1019010.5
G15: Cost Vendor | H15: =H11 -> 35213750
G16: Sisa LAB | H16: 6680833.3
H17: =H13+H14+H15+H16 -> 70287594 | I17: 71054951
H18: =H12-H17 -> 18614649

Sheet TOOLS-WORKING
B4: Lampiran 2
B5: No. | C5: ='Covering Letter '!D5 -> CS/0001/2025
B7: ADMINSITRATION
B8: No | C8: Section | D8: Tools | E8: Spec | F8: Qty | G8: Unit | H8: Unit Price | I8: Amount (Sub Total) | J8: Fee | L8: Amount (Total) | M8: Depre | N8: Amount
J9: % | K9: Amount
B10: 1 | C10: All | D10: Kertas | E10: A4 | F10: 5 | G10: Rim | H10: 62280 | I10: =F10*H10 -> 311400 | J10: 0.07 | K10: =I10*J10 -> 21798 | L10: =I10+K10 -> 333198 | M10: 1 | N10: =L10/M10 -> 333198 | P10: =N10/F10 -> 66639.6
B11: 2 | C11: All | D11: Bulpoint | F11: 1 | G11: Box | H11: 43200 | I11: =F11*H11 -> 43200 | J11: 0.07 | K11: =I11*J11 -> 3024 | L11: =I11+K11 -> 46224 | M11: 1 | N11: =L11/M11 -> 46224
B12: 3 | C12: All | D12: Printer | E12: Epson | F12: 2 | G12: Set | H12: 6280800 | I12: =F12*H12 -> 12561600 | J12: 0.07 | K12: =I12*J12 -> 879312 | L12: =I12+K12 -> 13440912 | M12: 12 | N12: 0
B13: 4 | C13: All | D13: Tinta Printer | E13: Epson | F13: 8 | G13: Set | H13: 413880 | I13: =F13*H13 -> 3311040 | J13: 0.07 | K13: =I13*J13 -> 231772.8 | L13: =I13+K13 -> 3542812.8 | M13: 1 | N13: =L13/M13 -> 3542812.8
B14: 5 | C14: All | D14: Laptop | F14: 0 | G14: Pcs | H14: 5000000 | I14: =F14*H14 -> 0 | J14: 0.07 | K14: =I14*J14 -> 0 | L14: =I14+K14 -> 0 | M14: 12 | N14: =L14/M14 -> 0
B15: 6 | C15: All | D15: Isi Label Printer | F15: 6 | G15: Pcs | H15: 287490 | I15: =F15*H15 -> 1724940 | J15: 0.07 | K15: =I15*J15 -> 120745.8 | L15: =I15+K15 -> 1845685.8 | M15: 12 | N15: =L15/M15 -> 153807.15
I16: =SUM(I10:I15) -> 17952180 | K16: =SUM(K10:K15) -> 1256652.6 | L16: =SUM(L10:L15) -> 19208833 | N16: =SUM(N10:N15) -> 4076041.9 | O16: =N16/4 -> 1019010.5 | P16: =N16/4 -> 1019010.5
B18: TOOLS ME
B19: No | C19: Section | D19: Tools | E19: Spec | F19: Qty | G19: Unit | H19: Unit Price | I19: Amount (Sub Total) | J19: Fee | L19: Amount (Total) | M19: Depre | N19: Amount
J20: % | K20: Amount
B21: 1 | C21: ME | D21: Thermal imager | F21: 0 | G21: Pcs | H21: 59938890 | I21: =F21*H21 -> 0 | J21: 0.07 | K21: =I21*J21 -> 0 | L21: 0 | M21: 24 | N21: =L21/M21 -> 0
B22: 2 | C22: ME | D22: Earth Tester | F22: 0 | G22: Pcs | H22: 4878000 | I22: =F22*H22 -> 0 | J22: 0.07 | K22: =I22*J22 -> 0 | L22: 0 | M22: 24 | N22: =L22/M22 -> 0
B23: 3 | C23: ME | D23: Clamp Meter | F23: 0 | G23: Pcs | H23: 2126400 | I23: =F23*H23 -> 0 | J23: 0.07 | K23: =I23*J23 -> 0 | L23: 0 | M23: 24 | N23: =L23/M23 -> 0
B24: 4 | C24: ME | D24: Digital Multimeter | F24: 0 | G24: Pcs | H24: 4993890 | I24: =F24*H24 -> 0 | J24: 0.07 | K24: =I24*J24 -> 0 | L24: 0 | M24: 24 | N24: =L24/M24 -> 0 | O24: https://www.googleadservices.com/pagead/aclk?sa=L&ai=DChcSEwiIvOD_kKuKAxUkq2YCHZMFIV8YABAeGgJzbQ&ae=2&aspm=1&co=1&ase=2&gclid=CjwKCAiAmfq6BhAsEiwAX1jsZ_QGaHB2PW1oPUaT4GGHHDTUeX516XLStuYNajgP-ZfTl1FDddMZJxoC3wcQAvD_BwE&ei=pIFfZ6qROfCw4-EP8qrfUQ&ohost=www.google.com&cid=CAESVuD21p6iXnmqKzspqtIJKe_Cy1xeozHnvbxt6WXSZoRw3JyvQTgr8JzGlA_AxzvdRfxSPLgEHZZoCSS5UISMcZx3wQWQMMFb8LAj_Q-IEgewMt8S1z-k&sig=AOD64_1Gq70GlvtY2XgNxXF1BRuL90wiBQ&ctype=5&q=&nis=4&sqi=2&ved=2ahUKEwiq89v_kKuKAxVw2DgGHXLVNwoQ9aACKAB6BAgHEA4&adurl=
B25: 5 | C25: ME | D25: Timah Solder | F25: 0 | G25: Pcs | H25: 94350 | I25: =F25*H25 -> 0 | J25: 0.07 | K25: =I25*J25 -> 0 | L25: 0 | M25: 12 | N25: =L25/M25 -> 0 | O25: https://www.monotaro.id/items/s018041712.html?utm_source=google&utm_medium=pla&utm_campaign=1672206402&utm_content=88187085595&gad_source=1&gclid=CjwKCAiAmfq6BhAsEiwAX1jsZ7Bd67bOftR7PMc9PNUjW3i6a9-ZVro2wd5QFDfWtXLxZCpBWxiTwxoCRQ0QAvD_BwE
B26: 6 | C26: ME | D26: Bor tangan listrik | F26: 0 | G26: Pcs | H26: 1774890 | I26: =F26*H26 -> 0 | J26: 0.07 | K26: =I26*J26 -> 0 | L26: 0 | M26: 24 | N26: =L26/M26 -> 0 | O26: https://www.monotaro.id/items/s000045017.html?utm_source=google&utm_medium=pla&utm_campaign=1672206402&utm_content=88187085595&gad_source=1&gclid=CjwKCAiAmfq6BhAsEiwAX1jsZ6i0fPuXI76hOnQrg7uWHPPMYS15tQ1lGoNZxZjgmxI-lXqRo6OsqhoCQx8QAvD_BwE | P26: New (NOK)
B27: 7 | C27: ME | D27: Bor tangan DC | F27: 0 | G27: Pcs | H27: 684600 | I27: =F27*H27 -> 0 | J27: 0.07 | K27: =I27*J27 -> 0 | L27: 0 | M27: 24 | N27: =L27/M27 -> 0 | P27: New (NOK)
B28: 8 | C28: ME | D28: Mesin Gerinda | F28: 0 | G28: Pcs | H28: 1604400 | I28: =F28*H28 -> 0 | J28: 0.07 | K28: =I28*J28 -> 0 | L28: 0 | M28: 24 | N28: =L28/M28 -> 0 | P28: New (NOK)
B29: 9 | C29: ME | D29: Vaccum Panel | F29: 0 | G29: Pcs | H29: 3519500 | I29: =F29*H29 -> 0 | J29: 0.07 | K29: =I29*J29 -> 0 | L29: 0 | M29: 24 | N29: =L29/M29 -> 0 | P29: 2024
B30: 10 | C30: ME | D30: Senter Kepala | F30: 4 | G30: Pcs | H30: 42000 | I30: =F30*H30 -> 168000 | J30: 0.07 | K30: =I30*J30 -> 11760 | L30: =I30+K30 -> 179760 | M30: 12 | N30: =L30/M30 -> 14980
B31: 11 | C31: ME | D31: Obeng Plus Kecil 100mm | F31: 0 | G31: Pcs | H31: 28000 | I31: =F31*H31 -> 0 | J31: 0.07 | K31: =I31*J31 -> 0 | L31: 0 | M31: 24 | N31: =L31/M31 -> 0 | P31: 2024
B32: 12 | C32: ME | D32: Obeng Plus Besar 200mm | F32: 0 | G32: Pcs | H32: 35000 | I32: =F32*H32 -> 0 | J32: 0.07 | K32: =I32*J32 -> 0 | L32: 0 | M32: 24 | N32: =L32/M32 -> 0 | P32: 2024
B33: 13 | C33: ME | D33: Obeng Min Kecil 100mm | F33: 0 | G33: Pcs | H33: 25000 | I33: =F33*H33 -> 0 | J33: 0.07 | K33: =I33*J33 -> 0 | L33: 0 | M33: 24 | N33: =L33/M33 -> 0 | P33: 2024
B34: 14 | C34: ME | D34: Obeng Min Besar 200mm | F34: 0 | G34: Pcs | H34: 40000 | I34: =F34*H34 -> 0 | J34: 0.07 | K34: =I34*J34 -> 0 | L34: 0 | M34: 24 | N34: =L34/M34 -> 0 | P34: 2024
B35: 15 | C35: ME | D35: Tang Snap Ring External 170mm | F35: 2 | G35: Pcs | H35: 150000 | I35: =F35*H35 -> 300000 | J35: 0.07 | K35: =I35*J35 -> 21000 | L35: =I35+K35 -> 321000 | M35: 12 | N35: =L35/M35 -> 26750 | P35: 2025
B36: 16 | C36: ME | D36: Tang Snap Ring Internal 170mm | F36: 2 | G36: Pcs | H36: 150000 | I36: =F36*H36 -> 300000 | J36: 0.07 | K36: =I36*J36 -> 21000 | L36: =I36+K36 -> 321000 | M36: 24 | N36: =L36/M36 -> 13375 | P36: 2025
B37: 17 | C37: ME | D37: Tang Potong / Plier Side Cutting 6" | F37: 3 | G37: Pcs | H37: 58000 | I37: =F37*H37 -> 174000 | J37: 0.07 | K37: =I37*J37 -> 12180 | L37: =I37+K37 -> 186180 | M37: 24 | N37: =L37/M37 -> 7757.5 | P37: 2025
B38: 18 | C38: ME | D38: Tang Jepit / Long Nouse 6" | F38: 0 | G38: Pcs | H38: 88000 | I38: =F38*H38 -> 0 | J38: 0.07 | K38: =I38*J38 -> 0 | L38: 0 | M38: 24 | N38: =L38/M38 -> 0 | P38: 2024
B39: 19 | C39: ME | D39: Tang Kombinasi / Plier Combination 7" | F39: 0 | G39: Pcs | H39: 63000 | I39: =F39*H39 -> 0 | J39: 0.07 | K39: =I39*J39 -> 0 | L39: 0 | M39: 24 | N39: =L39/M39 -> 0 | P39: 2024
B40: 20 | C40: ME | D40: Tang ripet | F40: 4 | G40: Pcs | H40: 100080 | I40: =F40*H40 -> 400320 | J40: 0.07 | K40: =I40*J40 -> 28022.4 | L40: =I40+K40 -> 428342.4 | M40: 12 | N40: =L40/M40 -> 35695.2 | P40: 2024
B41: 21 | C41: ME | D41: Kunci Pas 6-7 | F41: 2 | G41: Pcs | H41: 35900 | I41: =F41*H41 -> 71800 | J41: 0.07 | K41: =I41*J41 -> 5026 | L41: 0 | M41: 24 | N41: =L41/M41 -> 0 | P41: 2024
B42: 22 | C42: ME | D42: Kunci Pas 8-9 | F42: 2 | G42: Pcs | H42: 30000 | I42: =F42*H42 -> 60000 | J42: 0.07 | K42: =I42*J42 -> 4200 | L42: 0 | M42: 24 | N42: =L42/M42 -> 0 | P42: 2024
B43: 23 | C43: ME | D43: Kunci Pas 10-11 | F43: 2 | G43: Pcs | H43: 35000 | I43: =F43*H43 -> 70000 | J43: 0.07 | K43: =I43*J43 -> 4900 | L43: 0 | M43: 24 | N43: =L43/M43 -> 0 | P43: 2024
B44: 24 | C44: ME | D44: Kunci Pas 12-13 | F44: 2 | G44: Pcs | H44: 40000 | I44: =F44*H44 -> 80000 | J44: 0.07 | K44: =I44*J44 -> 5600 | L44: 0 | M44: 24 | N44: =L44/M44 -> 0 | P44: 2024
B45: 25 | C45: ME | D45: Kunci Pas 14-15 | F45: 2 | G45: Pcs | H45: 45000 | I45: =F45*H45 -> 90000 | J45: 0.07 | K45: =I45*J45 -> 6300 | L45: 0 | M45: 24 | N45: =L45/M45 -> 0 | P45: 2024
B46: 26 | C46: ME | D46: Kunci Pas 16-17 | F46: 2 | G46: Pcs | H46: 50000 | I46: =F46*H46 -> 100000 | J46: 0.07 | K46: =I46*J46 -> 7000 | L46: 0 | M46: 24 | N46: =L46/M46 -> 0 | P46: 2024
B47: 27 | C47: ME | D47: Kunci Inggris | F47: 2 | G47: Pcs | H47: 129000 | I47: =F47*H47 -> 258000 | J47: 0.07 | K47: =I47*J47 -> 18060 | L47: 0 | M47: 24 | N47: =L47/M47 -> 0 | P47: 2024
B48: 28 | C48: ME | D48: Cutter | F48: 10 | G48: Pcs | H48: 20000 | I48: =F48*H48 -> 200000 | J48: 0.07 | K48: =I48*J48 -> 14000 | L48: =I48+K48 -> 214000 | M48: 24 | N48: =L48/M48 -> 8916.6667 | P48: 2025
B49: 29 | C49: ME | D49: Ear Plug | F49: 2 | G49: Pcs | H49: 17500 | I49: =F49*H49 -> 35000 | J49: 0.07 | K49: =I49*J49 -> 2450 | L49: =I49+K49 -> 37450 | M49: 24 | N49: =L49/M49 -> 1560.4167 | P49: 2025
B50: 30 | C50: ME | D50: Kunci L set | F50: 2 | G50: Pcs | H50: 129000 | I50: =F50*H50 -> 258000 | J50: 0.07 | K50: =I50*J50 -> 18060 | L50: 0 | M50: 24 | N50: =L50/M50 -> 0 | P50: 2024
B51: 31 | C51: ME | D51: Roll meter 30 m/meteran | F51: 1 | G51: Pcs | H51: 89000 | I51: =F51*H51 -> 89000 | J51: 0.07 | K51: =I51*J51 -> 6230 | L51: 0 | M51: 24 | N51: =L51/M51 -> 0 | P51: 2024
B52: 32 | C52: ME | D52: Tang Crimping RJ11, 45 | E52: Tekiro | F52: 2 | G52: Pcs | H52: 205000 | I52: =F52*H52 -> 410000 | J52: 0.07 | K52: =I52*J52 -> 28700 | L52: =I52+K52 -> 438700 | M52: 24 | N52: =L52/M52 -> 18279.167 | P52: 2025
B53: 33 | C53: ME | D53: Kunci pipa kecil 12" | F53: 1 | G53: Pcs | H53: 85000 | I53: =F53*H53 -> 85000 | J53: 0.07 | K53: =I53*J53 -> 5950 | L53: =I53+K53 -> 90950 | M53: 24 | N53: =L53/M53 -> 3789.5833 | P53: 2025
B54: 34 | C54: ME | D54: Tangga almunium 1,5 M | F54: 1 | G54: Pcs | H54: 1108890 | I54: =F54*H54 -> 1108890 | J54: 0.07 | K54: =I54*J54 -> 77622.3 | L54: 0 | M54: 24 | N54: =L54/M54 -> 0 | P54: 2024
B55: 35 | C55: ME | D55: Tangga almunium 2 M | F55: 1 | G55: Pcs | H55: 2799000 | I55: =F55*H55 -> 2799000 | J55: 0.07 | K55: =I55*J55 -> 195930 | L55: 0 | M55: 24 | N55: =L55/M55 -> 0 | P55: 2024
B56: 36 | C56: ME | D56: Solder listrik 100 - 200 watt | F56: 2 | G56: Pcs | H56: 1774890 | I56: =F56*H56 -> 3549780 | J56: 0.07 | K56: =I56*J56 -> 248484.6 | L56: 0 | M56: 24 | N56: =L56/M56 -> 0 | O56: https://www.monotaro.id/items/s018026498.html?utm_source=google&utm_medium=pla&utm_campaign=1672206402&utm_content=88187085595&gad_source=1&gclid=CjwKCAiAmfq6BhAsEiwAX1jsZ2VC3dCTYcHBDeXDN4r_BoXn010XnL1f3yIHUiISYaelyMcgSpf0hxoCJKMQAvD_BwE | P56: 2024
B57: 37 | C57: ME | D57: Tas Pinggang | F57: 0 | G57: Pcs | H57: 243090 | I57: =F57*H57 -> 0 | J57: 0.07 | K57: =I57*J57 -> 0 | L57: 0 | M57: 12 | N57: =L57/M57 -> 0 | P57: New (NOK)
B58: 38 | C58: ME | D58: Tespen Kecil | F58: 3 | G58: Pcs | H58: 74400 | I58: =F58*H58 -> 223200 | J58: 0.07 | K58: =I58*J58 -> 15624 | L58: =I58+K58 -> 238824 | M58: 24 | N58: =L58/M58 -> 9951 | P58: 2025
B59: 39 | C59: ME | D59: Mata Bor Beton | F59: 1 | G59: set | H59: 265290 | I59: =F59*H59 -> 265290 | J59: 0.07 | K59: =I59*J59 -> 18570.3 | L59: 0 | M59: 12 | N59: =L59/M59 -> 0 | P59: New (NOK)
B60: 40 | C60: ME | D60: Gergaji Besi | F60: 2 | G60: Pcs | H60: 82800 | I60: =F60*H60 -> 165600 | J60: 0.07 | K60: =I60*J60 -> 11592 | L60: =I60+K60 -> 177192 | M60: 24 | N60: =L60/M60 -> 7383 | P60: 2025
B61: 41 | C61: ME | D61: Mata Bor Besi (Bosc) | F61: 1 | G61: set | H61: 387390 | I61: =F61*H61 -> 387390 | J61: 0.07 | K61: =I61*J61 -> 27117.3 | L61: 0 | M61: 12 | N61: =L61/M61 -> 0 | P61: New (NOK)
B62: 42 | C62: ME | D62: Obeng ketok + | F62: 1 | G62: Pcs | H62: 50000 | I62: =F62*H62 -> 50000 | J62: 0.07 | K62: =I62*J62 -> 3500 | L62: =I62+K62 -> 53500 | M62: 24 | N62: =L62/M62 -> 2229.1667 | P62: 2025
B63: 43 | C63: ME | D63: Obeng Ketok - | F63: 1 | G63: Pcs | H63: 45000 | I63: =F63*H63 -> 45000 | J63: 0.07 | K63: =I63*J63 -> 3150 | L63: =I63+K63 -> 48150 | M63: 24 | N63: =L63/M63 -> 2006.25 | P63: 2025
B64: 44 | C64: ME | D64: Obeng Cebol + (Tekiro) | F64: 1 | G64: Pcs | H64: 50000 | I64: =F64*H64 -> 50000 | J64: 0.07 | K64: =I64*J64 -> 3500 | L64: =I64+K64 -> 53500 | M64: 24 | N64: =L64/M64 -> 2229.1667 | P64: 2025
B65: 45 | C65: ME | D65: Obeng Cebol - (Tekiro) | F65: 1 | G65: Pcs | H65: 45000 | I65: =F65*H65 -> 45000 | J65: 0.07 | K65: =I65*J65 -> 3150 | L65: =I65+K65 -> 48150 | M65: 24 | N65: =L65/M65 -> 2006.25 | P65: 2025
B66: 46 | C66: ME | D66: Waterpass | F66: 1 | G66: Pcs | H66: 209790 | I66: =F66*H66 -> 209790 | J66: 0.07 | K66: =I66*J66 -> 14685.3 | L66: =I66+K66 -> 224475.3 | M66: 12 | N66: =L66/M66 -> 18706.275 | O66: https://www.monotaro.id/items/s013429041.html?utm_source=google&utm_medium=pla&utm_campaign=1672206402&utm_content=88187085595&gad_source=1&gclid=CjwKCAiAmfq6BhAsEiwAX1jsZ6OnRzuLxuyDkFVrjoL3ZRuoPKmWwsWnhambxc3jsMLwQRu_XNHQuhoCo1oQAvD_BwE | P66: 2025
B67: 47 | C67: ME | D67: Kunci shock | F67: 2 | G67: Set | H67: 1108890 | I67: =F67*H67 -> 2217780 | J67: 0.07 | K67: =I67*J67 -> 155244.6 | L67: =I67+K67 -> 2373024.6 | M67: 24 | N67: =L67/M67 -> 98876.025 | P67: 2025
B68: 48 | C68: ME | D68: Palu | F68: 2 | G68: Pcs | H68: 104400 | I68: =F68*H68 -> 208800 | J68: 0.07 | K68: =I68*J68 -> 14616 | L68: =I68+K68 -> 223416 | M68: 24 | N68: =L68/M68 -> 9309 | P68: 2025
B69: 49 | C69: ME | D69: Kunci Y 8,10,12 (Tekiro) | F69: 2 | G69: set | H69: 27000 | I69: =F69*H69 -> 54000 | J69: 0.07 | K69: =I69*J69 -> 3780 | L69: =I69+K69 -> 57780 | M69: 24 | N69: =L69/M69 -> 2407.5 | P69: 2025
B70: 50 | C70: ME | D70: Body Harnest | F70: 3 | G70: Pcs | H70: 709290 | I70: =F70*H70 -> 2127870 | J70: 0.07 | K70: =I70*J70 -> 148950.9 | L70: =I70+K70 -> 2276820.9 | M70: 24 | N70: =L70/M70 -> 94867.537 | P70: 2025
B71: 51 | C71: ME | D71: Sarung Tangan Listrik/Karet | F71: 3 | G71: Pcs | H71: 254190 | I71: =F71*H71 -> 762570 | J71: 0.07 | K71: =I71*J71 -> 53379.9 | L71: =I71+K71 -> 815949.9 | M71: 24 | N71: =L71/M71 -> 33997.912 | O71: https://www.monotaro.id/items/s018048995.html?utm_source=google&utm_medium=pla&utm_campaign=1672206402&utm_content=88187085595&gad_source=1&gclid=CjwKCAiAmfq6BhAsEiwAX1jsZ2T0trLH0RVu1xDtUChF1ac4XbKieuFsiTewsgvtCndQ6j5wAa-GhxoCm_4QAvD_BwE | P71: New 2025
B72: 52 | C72: ME | D72: Tang Lancip 6 Inchi | F72: 2 | G72: Pcs | H72: 187590 | I72: =F72*H72 -> 375180 | J72: 0.07 | K72: =I72*J72 -> 26262.6 | L72: =I72+K72 -> 401442.6 | M72: 12 | N72: =L72/M72 -> 33453.55 | O72: https://www.monotaro.id/items/s013202316.html?utm_source=google&utm_medium=pla&utm_campaign=1672206402&utm_content=88187085595&gad_source=1&gclid=CjwKCAiAmfq6BhAsEiwAX1jsZwGJEB8zREd_b9CXA3s1JXaOd_lYLVIZTeTZHMEF6-VhiETgb98HohoCgsMQAvD_BwE | P72: 2025
B73: 53 | C73: ME | D73: Kunci pipa | F73: 2 | G73: Pcs | H73: 267600 | I73: =F73*H73 -> 535200 | J73: 0.07 | K73: =I73*J73 -> 37464 | L73: =I73+K73 -> 572664 | M73: 12 | N73: =L73/M73 -> 47722 | P73: 2025
B74: 54 | C74: ME | D74: Kunci pipa kecil | F74: 2 | G74: Pcs | H74: 102000 | I74: =F74*H74 -> 204000 | J74: 0.07 | K74: =I74*J74 -> 14280 | L74: =I74+K74 -> 218280 | M74: 12 | N74: =L74/M74 -> 18190 | P74: 2025
B75: 55 | C75: ME | D75: Mechanic Tools Kit | F75: 2 | G75: set | H75: 1470600 | I75: =F75*H75 -> 2941200 | J75: 0.07 | K75: =I75*J75 -> 205884 | L75: =I75+K75 -> 3147084 | M75: 24 | N75: =L75/M75 -> 131128.5 | P75: 2025
B76: 56 | C76: ME | D76: Label Printer | F76: 1 | G76: Pcs | H76: 1219890 | I76: =F76*H76 -> 1219890 | J76: 0.07 | K76: =I76*J76 -> 85392.3 | L76: =I76+K76 -> 1305282.3 | M76: 12 | N76: =L76/M76 -> 108773.53 | P76: 2025
B77: 57 | C77: ME | D77: Jas Hujan | F77: 5 | G77: Pcs | H77: 301893 | I77: =F77*H77 -> 1509465 | J77: 0.07 | K77: =I77*J77 -> 105662.55 | L77: =I77+K77 -> 1615127.6 | M77: 6 | N77: =L77/M77 -> 269187.92 | P77: 2025
I78: =SUM(I21:I76) -> 22694550 | K78: =SUM(K21:K76) -> 1588618.5 | L78: =SUM(L21:L76) -> 14452918 | N78: =SUM(N21:N77) -> 1023528.1
B80: TOOLS AC
B81: No | C81: Section | D81: Tools | E81: Spec | F81: Qty | G81: Unit | H81: Unit Price | I81: Amount (Sub Total) | J81: Fee | L81: Amount (Total) | M81: Depre | N81: Amount
J82: % | K82: Amount
B83: 1 | C83: AC | D83: Selang Pompa Steam AC | E83: 1/4" | F83: 3 | G83: Pcs | H83: 390000 | I83: =F83*H83 -> 1170000 | J83: 0.07 | K83: =I83*J83 -> 81900 | L83: 0 | M83: 24 | N83: =L83/M83 -> 0 | O83: Odoo | P83: 2024
B84: 2 | C84: AC | D84: Plastik Service AC | E84: Split | F84: 3 | G84: Pcs | H84: 62000 | I84: =F84*H84 -> 186000 | J84: 0.07 | K84: =I84*J84 -> 13020 | L84: =I84+K84 -> 199020 | M84: 1 | N84: =L84/M84 -> 199020 | O84: https://www.tokopedia.com/ikieshop/plastik-cuci-ac-split-indoor-outdoor-unit?extParam=ivf%3Dfalse%26keyword%3Dplastik+cuci+ac%26search_id%3D20241031033649646EA4D1E603FA282ZH0%26src%3Dsearch | P84: 2025
B85: 3 | C85: AC | D85: Selang Air | E85: 5/8" | F85: 3 | G85: Pcs | H85: 235500 | I85: =F85*H85 -> 706500 | J85: 0.07 | K85: =I85*J85 -> 49455 | L85: =I85+K85 -> 755955 | M85: 12 | N85: =L85/M85 -> 62996.25 | O85: https://www.tokopedia.com/planetselang/paket-selang-air-30-meter-5-8-inch-tebal-1-mm-selang-air-serat-benang?src=topads | P85: 2025
B86: 4 | C86: AC | D86: Kabel Roll NYM 30 Meter | E86: 1.5 mm x 3 Supreme | F86: 3 | G86: Pcs | H86: 470000 | I86: =F86*H86 -> 1410000 | J86: 0.07 | K86: =I86*J86 -> 98700 | L86: 0 | M86: 24 | N86: =L86/M86 -> 0 | O86: https://www.tokopedia.com/ntelectric/supreme-kabel-nym-3x1-5-3-x-1-5-3x1-5-mm-putih-permeter?extParam=ivf%3Dfalse%26keyword%3Dkabel+nym+3x1+5+supreme%26search_id%3D20241031034313A07854F78A6F2C2ED0EW%26src%3Dsearch&refined=true | P86: 2024
B87: 5 | C87: AC | D87: Kanebo | E87: 32 x 21 cm | F87: 5 | G87: Pcs | H87: 15000 | I87: =F87*H87 -> 75000 | J87: 0.07 | K87: =I87*J87 -> 5250 | L87: =I87+K87 -> 80250 | M87: 2 | N87: =L87/M87 -> 40125 | O87: https://www.tokopedia.com/shanumelmyra/kain-lap-kanebo-ukuran-32-x-21-cm-lap-mobil-lap-motor-lap-sepeda-murah | P87: 2025
B88: 6 | C88: AC | D88: Senter Kepala/Headlamp | E88: LED CREE XML T6 | F88: 4 | G88: Pcs | H88: 35000 | I88: =F88*H88 -> 140000 | J88: 0.07 | K88: =I88*J88 -> 9800 | L88: =I88+K88 -> 149800 | M88: 3 | N88: =L88/M88 -> 49933.333 | O88: https://www.tokopedia.com/agenled/lampu-senter-kepala-led-30w-headlamp-cob-recharge-cas-charger-30-watt?extParam=ivf%3Dfalse&src=topads | P88: 2025
B89: 7 | C89: AC | D89: Tangga Lipat | E89: 3 Meter Alumunium | F89: 3 | G89: Pcs | H89: 1820000 | I89: =F89*H89 -> 5460000 | J89: 0.07 | K89: =I89*J89 -> 382200 | L89: 0 | M89: 24 | N89: =L89/M89 -> 0 | O89: Odoo | P89: 2024
B90: 8 | C90: AC | D90: Mesin Vacuum AC | E90: Value VE115N 1/4 HP | F90: 3 | G90: Pcs | H90: 1200000 | I90: =F90*H90 -> 3600000 | J90: 0.07 | K90: =I90*J90 -> 252000 | L90: =I90+K90 -> 3852000 | M90: 12 | N90: =L90/M90 -> 321000 | O90: https://www.tokopedia.com/jefry1fernando/vacum-pump-ac-1-4-pk-vacuum-pump-mobil-dan-kulkas-value-ve115n?extParam=ivf%3Dfalse%26keyword%3Dve115n%26search_id%3D20241031040051646EA4D1E603FA30DQZ3%26src%3Dsearch | P90: 2025
B91: 9 | C91: AC | D91: Cutter Pipa Tube | E91: CT-128 | F91: 3 | G91: Pcs | H91: 24000 | I91: =F91*H91 -> 72000 | J91: 0.07 | K91: =I91*J91 -> 5040 | L91: =I91+K91 -> 77040 | M91: 12 | N91: =L91/M91 -> 6420 | O91: https://www.tokopedia.com/kontinumabadi/tube-cutter-alat-pemotong-pipa-ac-ct-128 | P91: 2025
B92: 10 | C92: AC | D92: Flaring Tools AC | E92: Value VFT-808-IN | F92: 3 | G92: Pcs | H92: 535000 | I92: =F92*H92 -> 1605000 | J92: 0.07 | K92: =I92*J92 -> 112350 | L92: 0 | M92: 24 | N92: =L92/M92 -> 0 | O92: https://www.tokopedia.com/gendosparepart/value-flaring-tool-vft-808-in | P92: 2024
B93: 11 | C93: AC | D93: Thermogun | E93: WH320 | F93: 3 | G93: Pcs | H93: 166000 | I93: =F93*H93 -> 498000 | J93: 0.07 | K93: =I93*J93 -> 34860 | L93: 0 | M93: 12 | N93: =L93/M93 -> 0 | O93: https://www.tokopedia.com/binaelectric/industrial-infrared-thermogun-wh320-dv-thermometer-gun-dv-celcius | P93: 2024
B94: 12 | C94: AC | D94: Solder Listrik | E94: IRON 60 Watt | F94: 2 | G94: Pcs | H94: 40000 | I94: =F94*H94 -> 80000 | J94: 0.07 | K94: =I94*J94 -> 5600 | L94: =I94+K94 -> 85600 | M94: 12 | N94: =L94/M94 -> 7133.3333 | O94: https://www.tokopedia.com/mangjajang/solder-listrik-iron-60w-adjustable-temperatur-200-450-c-solder?extParam=ivf%3Dfalse%26keyword%3Dsolder+60+watt%26search_id%3D202410310405080801EAA2BB119B2D5Q4G%26src%3Dsearch%26whid%3D12669178 | P94: 2025
B95: 13 | C95: AC | D95: Manifold | E95: DBL B536 Multi/500 | F95: 1 | G95: Pcs | H95: 200000 | I95: =F95*H95 -> 200000 | J95: 0.07 | K95: =I95*J95 -> 14000 | L95: 0 | M95: 12 | N95: =L95/M95 -> 0 | O95: https://www.tokopedia.com/terataianeka/testing-manifold-ac-double-multi-r22-r134a-r410a-r32-starmec-dbl-b536 | P95: 2024
B96: 14 | C96: AC | D96: Manifold | E96: VMG-2-R410A-B-02 | F96: 1 | G96: Pcs | H96: 650000 | I96: =F96*H96 -> 650000 | J96: 0.07 | K96: =I96*J96 -> 45500 | L96: 0 | M96: 12 | N96: =L96/M96 -> 0 | O96: https://www.tokopedia.com/injaya21/manifold-value-r410-vmg-r410a-b-02-manifold-double-multi-r22-r410 | P96: 2024
B97: 15 | C97: AC | D97: Manifold | E97: PGD-536GF | F97: 1 | G97: Pcs | H97: 290000 | I97: =F97*H97 -> 290000 | J97: 0.07 | K97: =I97*J97 -> 20300 | L97: 0 | M97: 12 | N97: =L97/M97 -> 0 | O97: https://shopee.co.id/Testing-Manifold-STARMEC-PGD-536GF-Double-Manifold-PGD536-GF-STARMEC-i.233341203.7534553994 | P97: 2024
B98: 16 | C98: AC | D98: Timah Solder | E98: 0.6mm Asahi | F98: 5 | G98: Pcs | H98: 150000 | I98: =F98*H98 -> 750000 | J98: 0.07 | K98: =I98*J98 -> 52500 | L98: =I98+K98 -> 802500 | M98: 3 | N98: =L98/M98 -> 267500 | O98: https://www.tokopedia.com/bentshops/timah-asahi-0-6-mm-60-40-timah-solder-asahi-original?extParam=ivf%3Dfalse&src=topads | P98: 2025
B99: 17 | C99: AC | D99: Pompa Steam | E99: Moris MOR-409 | F99: 2 | G99: Pcs | H99: 950000 | I99: =F99*H99 -> 1900000 | J99: 0.07 | K99: =I99*J99 -> 133000 | L99: =I99+K99 -> 2033000 | M99: 12 | N99: =L99/M99 -> 169416.67 | O99: https://www.tokopedia.com/remajateknik88/jet-ac-cleaner-high-pressure-nlg-hpc-40-ts-alternatif-morris-40p-unit-saja-bawaan-5-meter-0f514?extParam=ivf%3Dfalse&src=topads | P99: 2025
B100: 18 | C100: AC | D100: Mesin Las Acetylene | E100: MMA 500 | F100: 1 | G100: Pcs | H100: 3400000 | I100: =F100*H100 -> 3400000 | J100: 0.07 | K100: =I100*J100 -> 238000 | L100: 0 | M100: 12 | N100: =L100/M100 -> 0 | O100: https://tokopedia.link/X6cW41nE8Nb | P100: 2024
B101: 19 | C101: AC | D101: Ember Besar | F101: 5 | G101: Pcs | H101: 79900 | I101: =F101*H101 -> 399500 | J101: 0.07 | K101: =I101*J101 -> 27965 | L101: 0 | M101: 24 | N101: =L101/M101 -> 0 | O101: https://tokopedia.link/CXRpB1AE8Nb | P101: 2024
B102: 20 | C102: AC | D102: Kunci Y | E102: Tekiro | F102: 2 | G102: Pcs | H102: 27000 | I102: =F102*H102 -> 54000 | J102: 0.07 | K102: =I102*J102 -> 3780 | L102: =I102+K102 -> 57780 | M102: 12 | N102: =L102/M102 -> 4815 | O102: https://tokopedia.link/sb9Tf1ME8Nb | P102: 2025
B103: 21 | C103: AC | D103: Trolley | F103: 2 | G103: Pcs | H103: 599900 | I103: =F103*H103 -> 1199800 | J103: 0.07 | K103: =I103*J103 -> 83986 | L103: =I103+K103 -> 1283786 | M103: 12 | N103: =L103/M103 -> 106982.17 | O103: https://tokopedia.link/jYIZWzZE8Nb | P103: 2025
B104: 22 | C104: AC | D104: Kunci Inggris | F104: 3 | G104: Pcs | H104: 107500 | I104: =F104*H104 -> 322500 | J104: 0.07 | K104: =I104*J104 -> 22575 | L104: 0 | M104: 24 | N104: =L104/M104 -> 0 | O104: https://tokopedia.link/VCltXBOH8Nb
B105: 23 | C105: AC | D105: Terpal | F105: 3 | G105: Pcs | H105: 368000 | I105: =F105*H105 -> 1104000 | J105: 0.07 | K105: =I105*J105 -> 77280 | L105: =I105+K105 -> 1181280 | M105: 12 | N105: =L105/M105 -> 98440 | O105: https://tokopedia.link/yHWGVThF8Nb | P105: 2025
B106: 24 | C106: AC | D106: R22 | E106: Netto : 13,6kg, Bruto : 16,5kg | F106: 5 | G106: Pcs | H106: 1225000 | I106: =F106*H106 -> 6125000 | J106: 0.07 | K106: =I106*J106 -> 428750 | L106: =I106+K106 -> 6553750 | M106: 3 | N106: =L106/M106 -> 2184583.3 | O106: https://www.tokopedia.com/technicamarket/freon-refrigerant-22-r22?extParam=ivf%3Dfalse%26keyword%3Dfreon+refrigerant+r22&src=topads | P106: 2025
...

Sheet TOOLS
B5: Lampiran 2
B6: No. | C6: ='[1]Covering Letter '!D5 -> CS/0202/2025
B8: BIAYA PERALATAN MAINTENANCE PER BULAN
B9: TAHUN 2025
B10: NAMA | D10: PT MITRA BAKTI UT
B11: AREA PELAYANAN | D11: PT UNITED TRACTORS TBK - HEAD OFFICE
B13: A. PERALATAN ADMINISTRATION
B14: No | C14: Keterangan | D14: Kuantitas | F14: Harga | G14: Biaya | H14: Depr | I14: Biaya / bln
B15: 1 | C15: Kertas | D15: 5 | E15: Rim | F15: 66639.6 | G15: =D15*F15 -> 333198 | H15: 1 | I15: =G15/H15 -> 333198
B16: 2 | C16: Bulpoint | D16: 1 | E16: Box | F16: 46224 | G16: =D16*F16 -> 46224 | H16: 1 | I16: =G16/H16 -> 46224
B17: 3 | C17: Printer | D17: 2 | E17: Set | F17: 6720456 | G17: 0 | H17: 12 | I17: =G17/H17 -> 0
B18: 4 | C18: Tinta Printer | D18: 8 | E18: Set | F18: 442851.6 | G18: =F18*D18 -> 3542812.8 | H18: 1 | I18: =G18/H18 -> 3542812.8
B19: 5 | C19: Laptop | D19: 9 | E19: Pcs | F19: 5350000 | G19: 0 | H19: 12 | I19: =G19/H19 -> 0
B20: 6 | C20: Isi Label Printer | D20: 6 | E20: Pcs | F20: 307614.3 | G20: =F20*D20 -> 1845685.8 | H20: 12 | I20: =G20/H20 -> 153807.15
B21: TOTAL | I21: =SUM(I15:I20) -> 4076042 | J21: =I21/4 -> 1019010.5
J22: =I21/107% -> 3809385
B23: B. PERALATAN ME | J23: =I21-J22 -> 266656.95
B24: No | C24: Keterangan | D24: Kuantitas | F24: Harga | G24: Biaya | H24: Depr | I24: Biaya / bln
B25: 1 | C25: Thermal Imager | D25: 0 | E25: Pcs | F25: 64134612 | G25: =D25*F25 -> 0 | H25: 24 | I25: =G25/H25 -> 0
B26: 2 | C26: Earth Tester | D26: 0 | E26: Pcs | F26: 5219460 | G26: =D26*F26 -> 0 | H26: 24 | I26: =G26/H26 -> 0
B27: 3 | C27: Clamp Meter | D27: 0 | E27: Pcs | F27: 2275248 | G27: =D27*F27 -> 0 | H27: 24 | I27: =G27/H27 -> 0
B28: 4 | C28: Digital Multimeter | D28: 0 | E28: Pcs | F28: 5343462.3 | G28: =D28*F28 -> 0 | H28: 24 | I28: =G28/H28 -> 0
B29: 5 | C29: Timah Solder | D29: 0 | E29: Pcs | F29: 100954.5 | G29: =D29*F29 -> 0 | H29: 12 | I29: =G29/H29 -> 0
B30: 6 | C30: Bor Tangan Listrik | D30: 0 | E30: Pcs | F30: 1899132.3 | G30: =D30*F30 -> 0 | H30: 24 | I30: =G30/H30 -> 0
B31: 7 | C31: Bor Tangan DC | D31: 0 | E31: Pcs | F31: 732522 | G31: =D31*F31 -> 0 | H31: 24 | I31: =G31/H31 -> 0
B32: 8 | C32: Mesin Gerinda | D32: 0 | E32: Pcs | F32: 1716708 | G32: =D32*F32 -> 0 | H32: 24 | I32: =G32/H32 -> 0
B33: 9 | C33: Vaccum Panel | D33: 0 | E33: Pcs | F33: 3765865 | G33: =D33*F33 -> 0 | H33: 24 | I33: =G33/H33 -> 0
B34: 10 | C34: Senter Kepala | D34: 4 | E34: Pcs | F34: 44940 | G34: =D34*F34 -> 179760 | H34: 12 | I34: =G34/H34 -> 14980
B35: 11 | C35: Obeng Plus Kecil 100mm | D35: 0 | E35: Pcs | F35: 29960 | G35: =D35*F35 -> 0 | H35: 24 | I35: =G35/H35 -> 0
B36: 12 | C36: Obeng Plus Besar 200mm | D36: 0 | E36: Pcs | F36: 37450 | G36: =D36*F36 -> 0 | H36: 24 | I36: =G36/H36 -> 0
... B44: 20 | C44: Tang Ripet | D44: 4 | E44: Pcs | F44: 107085.6 | G44: =D44*F44 -> 428342.4 | H44: 12 | I44: =G44/H44 -> 35695.2
B45: 21 | C45: Kunci Pas 6-7 | D45: 2 | E45: Pcs | F45: 38413 | G45: =D45*F45*0 -> 0 | H45: 24 | I45: =G45/H45 -> 0
B46: 22 | C46: Kunci Pas 8-9 | D46: 2 | E46: Pcs | F46: 32100 | G46: =D46*F46*0 -> 0 | H46: 24 | I46: =G46/H46 -> 0
B47: 23 | C47: Kunci Pas 10-11 | D47: 2 | E47: Pcs | F47: 37450 | G47: =D47*F47*0 -> 0 | H47: 24 | I47: =G47/H47 -> 0
B48: 24 | C48: Kunci Pas 12-13 | D48: 2 | E48: Pcs | F48: 42800 | G48: =D48*F48*0 -> 0 | H48: 24 | I48: =G48/H48 -> 0
B49: 25 | C49: Kunci Pas 14-15 | D49: 2 | E49: Pcs | F49: 48150 | G49: =D49*F49*0 -> 0 | H49: 24 | I49: =G49/H49 -> 0
B50: 26 | C50: Kunci Pas 16-17 | D50: 2 | E50: Pcs | F50: 53500 | G50: =D50*F50*0 -> 0 | H50: 24 | I50: =G50/H50 -> 0
B51: 27 | C51: Kunci Inggris | D51: 2 | E51: Pcs | F51: 138030 | G51: =D51*F51*0 -> 0 | H51: 24 | I51: =G51/H51 -> 0
B52: 28 | C52: Cutter | D52: 10 | E52: Pcs | F52: 21400 | G52: =D52*F52 -> 214000 | H52: 24 | I52: =G52/H52 -> 8916.6667
B53: 29 | C53: Ear Plug | D53: 2 | E53: Pcs | F53: 18725 | G53: =D53*F53 -> 37450 | H53: 24 | I53: =G53/H53 -> 1560.4167
B54: 30 | C54: Kunci L Set | D54: 2 | E54: Pcs | F54: 138030 | G54: =D54*F54*0 -> 0 | H54: 24 | I54: =G54/H54 -> 0
B55: 31 | C55: Roll Meter 30 M/Meteran | D55: 1 | E55: Pcs | F55: 95230 | G55: =D55*F55*0 -> 0 | H55: 24 | I55: =G55/H55 -> 0
B56: 32 | C56: Tang Crimping RJ11, 45 | D56: 2 | E56: Pcs | F56: 219350 | G56: =D56*F56 -> 438700 | H56: 24 | I56: =G56/H56 -> 18279.167
B57: 33 | C57: Kunci Pipa Kecil 12" | D57: 1 | E57: Pcs | F57: 90950 | G57: =D57*F57 -> 90950 | H57: 24 | I57: =G57/H57 -> 3789.5833
B58: 34 | C58: Tangga Almunium 1,5 M | D58: 1 | E58: Pcs | F58: 1186512.3 | G58: =D58*F58*0 -> 0 | H58: 24 | I58: =G58/H58 -> 0
B59: 35 | C59: Tangga Almunium 2 M | D59: 1 | E59: Pcs | F59: 2994930 | G59: =D59*F59*0 -> 0 | H59: 24 | I59: =G59/H59 -> 0
B60: 36 | C60: Solder Listrik 100 - 200 Watt | D60: 2 | E60: Pcs | F60: 1899132.3 | G60: =D60*F60*0 -> 0 | H60: 24 | I60: =G60/H60 -> 0
B61: 37 | C61: Tas Pinggang | D61: 0 | E61: Pcs | F61: 260106.3 | G61: =D61*F61 -> 0 | H61: 12 | I61: =G61/H61 -> 0
B62: 38 | C62: Tespen Kecil | D62: 3 | E62: Pcs | F62: 79608 | G62: =D62*F62 -> 238824 | H62: 24 | I62: =G62/H62 -> 9951
B63: 39 | C63: Mata Bor Beton | D63: 1 | E63: set | F63: 283860.3 | G63: =D63*F63*0 -> 0 | H63: 12 | I63: =G63/H63 -> 0
B64: 40 | C64: Gergaji Besi | D64: 2 | E64: Pcs | F64: 88596 | G64: =D64*F64 -> 177192 | H64: 24 | I64: =G64/H64 -> 7383
B65: 41 | C65: Mata Bor Besi (Bosc) | D65: 1 | E65: set | F65: 414507.3 | G65: =D65*F65*0 -> 0 | H65: 12 | I65: =G65/H65 -> 0
B66: 42 | C66: Obeng Ketok + | D66: 1 | E66: Pcs | F66: 53500 | G66: =D66*F66 -> 53500 | H66: 24 | I66: =G66/H66 -> 2229.1667
B67: 43 | C67: Obeng Ketok - | D67: 1 | E67: Pcs | F67: 48150 | G67: =D67*F67 -> 48150 | H67: 24 | I67: =G67/H67 -> 2006.25
B68: 44 | C68: Obeng Cebol + (Tekiro) | D68: 1 | E68: Pcs | F68: 53500 | G68: =D68*F68 -> 53500 | H68: 24 | I68: =G68/H68 -> 2229.1667
B69: 45 | C69: Obeng Cebol - (Tekiro) | D69: 1 | E69: Pcs | F69: 48150 | G69: =D69*F69 -> 48150 | H69: 24 | I69: =G69/H69 -> 2006.25
B70: 46 | C70: Waterpass | D70: 1 | E70: Pcs | F70: 224475.3 | G70: =D70*F70 -> 224475.3 | H70: 12 | I70: =G70/H70 -> 18706.275
B71: 47 | C71: Kunci Shock | D71: 2 | E71: Set | F71: 1186512.3 | G71: =D71*F71 -> 2373024.6 | H71: 24 | I71: =G71/H71 -> 98876.025
B72: 48 | C72: Palu | D72: 2 | E72: Pcs | F72: 111708 | G72: =D72*F72 -> 223416 | H72: 24 | I72: =G72/H72 -> 9309
B73: 49 | C73: Kunci Y 8,10,12 (Tekiro) | D73: 2 | E73: set | F73: 28890 | G73: =D73*F73 -> 57780 | H73: 24 | I73: =G73/H73 -> 2407.5
B74: 50 | C74: Body Harnest | D74: 3 | E74: Pcs | F74: 758940.3 | G74: =D74*F74 -> 2276820.9 | H74: 24 | I74: =G74/H74 -> 94867.538
B75: 51 | C75: Sarung Tangan Listrik/Karet | D75: 3 | E75: Pcs | F75: 271983.3 | G75: =D75*F75 -> 815949.9 | H75: 24 | I75: =G75/H75 -> 33997.912
B76: 52 | C76: Tang Lancip 6 Inchi | D76: 2 | E76: Pcs | F76: 200721.3 | G76: =D76*F76 -> 401442.6 | H76: 12 | I76: =G76/H76 -> 33453.55
B77: 53 | C77: Kunci Pipa | D77: 2 | E77: Pcs | F77: 286332 | G77: =D77*F77 -> 572664 | H77: 12 | I77: =G77/H77 -> 47722
... B81: 57 | C81: Jas Hujan | D81: 5 | E81: Pcs | F81: 323025.51 | G81: =D81*F81 -> 1615127.6 | H81: 6 | I81: =G81/H81 -> 269187.92
B82: 58 | C82: Smoke Test 70gr | D82: 400 | E82: botol | F82: =133000*120% -> 159600 | G82: =D82*F82 -> 63840000 | H82: 12 | I82: =G82/H82 -> 5320000
B83: TOTAL | I83: =SUM(I25:I82) -> 6343528.1 | J83: =I83/107% -> 5928531
J84: =I83-J83 -> 414997.17
B85: C. PERALATAN AC
B86: No | C86: Keterangan | D86: Kuantitas | F86: Harga | G86: Biaya | H86: Depr | I86: Biaya / bln
B87: 1 | C87: Selang Pompa Steam AC | D87: 3 | E87: Pcs | F87: 417300 | G87: =D87*F87*0 -> 0 | H87: 24 | I87: =G87/H87 -> 0
B88: 2 | C88: Plastik Service AC | D88: 3 | E88: Pcs | F88: 66340 | G88: =D88*F88 -> 199020 | H88: 1 | I88: =G88/H88 -> 199020
B89: 3 | C89: Selang Air | D89: 3 | E89: Pcs | F89: 251985 | G89: =D89*F89 -> 755955 | H89: 12 | I89: =G89/H89 -> 62996.25
B90: 4 | C90: Kabel Roll Nym 30 Meter | D90: 3 | E90: Pcs | F90: 502900 | G90: =D90*F90*0 -> 0 | H90: 24 | I90: =G90/H90 -> 0
B91: 5 | C91: Kanebo | D91: 5 | E91: Pcs | F91: 16050 | G91: =D91*F91 -> 80250 | H91: 2 | I91: =G91/H91 -> 40125
B92: 6 | C92: Senter Kepala/Headlamp | D92: 4 | E92: Pcs | F92: 37450 | G92: =D92*F92 -> 149800 | H92: 3 | I92: =G92/H92 -> 49933.333
B93: 7 | C93: Tangga Lipat | D93: 3 | E93: Pcs | F93: 1947400 | G93: =D93*F93*0 -> 0 | H93: 24 | I93: =G93/H93 -> 0
B94: 8 | C94: Mesin Vacuum AC | D94: 3 | E94: Pcs | F94: 1284000 | G94: =D94*F94 -> 3852000 | H94: 12 | I94: =G94/H94 -> 321000
B95: 9 | C95: Cutter Pipa Tube | D95: 3 | E95: Pcs | F95: 25680 | G95: =D95*F95 -> 77040 | H95: 12 | I95: =G95/H95 -> 6420
B96: 10 | C96: Flaring Tools AC | D96: 3 | E96: Pcs | F96: 572450 | G96: =D96*F96*0 -> 0 | H96: 24 | I96: =G96/H96 -> 0
B97: 11 | C97: Thermogun | D97: 3 | E97: Pcs | F97: 177620 | G97: =D97*F97*0 -> 0 | H97: 12 | I97: =G97/H97 -> 0
B98: 12 | C98: Solder Listrik | D98: 2 | E98: Pcs | F98: 42800 | G98: =D98*F98 -> 85600 | H98: 12 | I98: =G98/H98 -> 7133.3333
B99: 13 | C99: Manifold | D99: 1 | E99: Pcs | F99: 214000 | G99: =D99*F99*0 -> 0 | H99: 12 | I99: =G99/H99 -> 0
B100: 14 | C100: Manifold | D100: 1 | E100: Pcs | F100: 695500 | G100: =D100*F100*0 -> 0 | H100: 12 | I100: =G100/H100 -> 0
B101: 15 | C101: Manifold | D101: 1 | E101: Pcs | F101: 310300 | G101: =D101*F101*0 -> 0 | H101: 12 | I101: =G101/H101 -> 0
B102: 16 | C102: Timah Solder | D102: 5 | E102: Pcs | F102: 160500 | G102: =D102*F102 -> 802500 | H102: 3 | I102: =G102/H102 -> 267500
B103: 17 | C103: Pompa Steam | D103: 2 | E103: Pcs | F103: 1016500 | G103: =D103*F103 -> 2033000 | H103: 12 | I103: =G103/H103 -> 169416.67
B104: 18 | C104: Mesin Las Acetylene | D104: 1 | E104: Pcs | F104: 3638000 | G104: =D104*F104*0 -> 0 | H104: 12 | I104: =G104/H104 -> 0
B105: 19 | C105: Ember Besar | D105: 5 | E105: Pcs | F105: 85493 | G105: =D105*F105*0 -> 0 | H105: 24 | I105: =G105/H105 -> 0
B106: 20 | C106: Kunci Y | D106: 2 | E106: Pcs | F106: 28890 | G106: =D106*F106 -> 57780 | H106: 12 | I106: =G106/H106 -> 4815
B107: 21 | C107: Trolley | D107: 2 | E107: Pcs | F107: 641893 | G107: =D107*F107 -> 1283786 | H107: 12 | I107: =G107/H107 -> 106982.17
B108: 22 | C108: Kunci Inggris | D108: 3 | E108: Pcs | F108: 115025 | G108: =D108*F108*0 -> 0 | H108: 24 | I108: =G108/H108 -> 0
B109: 23 | C109: Terpal | D109: 3 | E109: Pcs | F109: 393760 | G109: =D109*F109 -> 1181280 | H109: 12 | I109: =G109/H109 -> 98440
B110: 24 | C110: R22 | D110: 5 | E110: Pcs | F110: 1310750 | G110: =D110*F110 -> 6553750 | H110: 3 | I110: =G110/H110 -> 2184583.3
B111: 25 | C111: R41 | D111: 10 | E111: Pcs | F111: 1273300 | G111: =D111*F111 -> 12733000 | H111: 3 | I111: =G111/H111 -> 4244333.3
B112: 26 | C112: R32 | D112: 5 | E112: Pcs | F112: 1230500 | G112: =D112*F112 -> 6152500 | H112: 3 | I112: =G112/H112 -> 2050833.3
B113: 27 | C113: Tang Kombinasi Uk 8 Inc | D113: 4 | E113: Pcs | F113: 41730 | G113: =D113*F113*0 -> 0 | H113: 24 | I113: =G113/H113 -> 0
B114: 28 | C114: Kunci L Bintang | D114: 1 | E114: Pcs | F114: 300135 | G114: =D114*F114*0 -> 0 | H114: 24 | I114: =G114/H114 -> 0
B115: 29 | C115: Meteran 5 Mtr | D115: 2 | E115: Pcs | F115: 32100 | G115: =D115*F115*0 -> 0 | H115: 24 | I115: =G115/H115 -> 0
B116: 30 | C116: Kunci L Biasa | D116: 1 | E116: Pcs | F116: 139100 | G116: =D116*F116*0 -> 0 | H116: 24 | I116: =G116/H116 -> 0
...

Sheet TOOLS-PRINT
B4: Lampiran 2
B5: No. | C5: ='Covering Letter '!D5 -> CS/0001/2025
B7: BIAYA PERALATAN MAINTENANCE PER BULAN
B8: TAHUN 2025
B9: NAMA | D9: PT MITRA BAKTI UT
B10: AREA PELAYANAN | D10: PT UNITED TRACTORS TBK - HEAD OFFICE
B12: A. PERALATAN ADMINISTRATION
B13: No | C13: Keterangan | D13: Kuantitas | F13: Depr
B14: 1 | C14: Kertas | D14: 5 | E14: Rim | F14: 1
B15: 2 | C15: Bulpoint | D15: 1 | E15: Box | F15: 1
B16: 3 | C16: Printer | D16: 0 | E16: Set | F16: 12
B17: 4 | C17: Tinta Printer | D17: 8 | E17: Set | F17: 1
B18: 5 | C18: Laptop | D18: 0 | E18: Pcs | F18: 12
B19: 6 | C19: Isi Label Printer | D19: 6 | E19: Pcs | F19: 12
B20: TOTAL | G20: =#REF!/4 -> #REF!
B22: B. PERALATAN ME
B23: No | C23: Keterangan | D23: Kuantitas | F23: Depr
B24: 1 | C24: Thermal Imager | D24: 0 | E24: Pcs | F24: 24
B25: 2 | C25: Earth Tester | D25: 0 | E25: Pcs | F25: 24
B26: 3 | C26: Clamp Meter | D26: 0 | E26: Pcs | F26: 24
B27: 4 | C27: Digital Multimeter | D27: 0 | E27: Pcs | F27: 24
B28: 5 | C28: Timah Solder | D28: 0 | E28: Pcs | F28: 12
B29: 6 | C29: Bor Tangan Listrik | D29: 0 | E29: Pcs | F29: 24
B30: 7 | C30: Bor Tangan DC | D30: 0 | E30: Pcs | F30: 24
B31: 8 | C31: Mesin Gerinda | D31: 0 | E31: Pcs | F31: 24
B32: 9 | C32: Vaccum Panel | D32: 0 | E32: Pcs | F32: 24
B33: 10 | C33: Senter Kepala | D33: 4 | E33: Pcs | F33: 12
B34: 11 | C34: Obeng Plus Kecil 100mm | D34: 0 | E34: Pcs | F34: 24
B35: 12 | C35: Obeng Plus Besar 200mm | D35: 0 | E35: Pcs | F35: 24
... B81: 58 | C81: Smoke Test 70gr | D81: 400 | E81: botol | F81: 12
B82: TOTAL
B84: C. PERALATAN AC
B85: No | C85: Keterangan | D85: Kuantitas | F85: Depr
B86: 1 | C86: Selang Pompa Steam AC | D86: 0 | E86: Pcs | F86: 24
B87: 2 | C87: Plastik Service AC | D87: 3 | E87: Pcs | F87: 1
B88: 3 | C88: Selang Air | D88: 3 | E88: Pcs | F88: 12
B89: 4 | C89: Kabel Roll Nym 30 Meter | D89: 0 | E89: Pcs | F89: 24
B90: 5 | C90: Kanebo | D90: 5 | E90: Pcs | F90: 2
B91: 6 | C91: Senter Kepala/Headlamp | D91: 4 | E91: Pcs | F91: 3
B92: 7 | C92: Tangga Lipat | D92: 0 | E92: Pcs | F92: 24
B93: 8 | C93: Mesin Vacuum AC | D93: 3 | E93: Pcs | F93: 12
B94: 9 | C94: Cutter Pipa Tube | D94: 3 | E94: Pcs | F94: 12
B95: 10 | C95: Flaring Tools AC | D95: 0 | E95: Pcs | F95: 24
B96: 11 | C96: Thermogun | D96: 0 | E96: Pcs | F96: 12
B97: 12 | C97: Solder Listrik | D97: 2 | E97: Pcs | F97: 12
... B141: 56 | C141: Checmical | D141: 20 | E141: Liter | F141: 12
B142: TOTAL
B144: D. PERALATAN CIVIL
B145: No | C145: Keterangan | D145: Kuantitas | F145: Depr
B146: 1 | C146: Jack Hammer (set) | D146: 1 | E146: Set | F146: 12
B147: 2 | C147: Gerobag Celeng | D147: 0 | E147: Pcs | F147: 12
B148: 3 | C148: Meteran | D148: 2 | E148: Pcs | F148: 12
B149: 4 | C149: Hair drayer | D149: 1 | E149: Pcs | F149: 12
B150: 5 | C150: Meteran uk. 5 mtr | D150: 2 | E150: Pcs | F150: 12
B151: 6 | C151: Meteran laser/digital | D151: 1 | E151: Pcs | F151: 12
B152: 7 | C152: Meteran jangka sorong | D152: 2 | E152: Pcs | F152: 12
B153: 8 | C153: Waterpass | D153: 1 | E153: Pcs | F153: 12
B154: 9 | C154: Obeng min (-) | D154: 2 | E154: set | F154: 12
B155: 10 | C155: Obeng plus (+) | D155: 2 | E155: set | F155: 12
B156: 11 | C156: Sepatu Booth | D156: 2 | E156: Pcs | F156: 1
B157: 12 | C157: Jas Hujan | D157: 3 | E157: Pcs | F157: 6
... B159: 14 | C159: Mata bor | D159: 3 | E159: set | F159: 2
B160: TOTAL

Sheet LIST MP
B5: Lampiran 2
B6: No. | C6: ='Covering Letter '!D5 -> CS/0001/2025
B9: TENAGA KERJA JOB SUPPLY MAINTENANCE
B10: NAMA | D10: : PT MITRA BAKTI UT
B11: AREA PELAYANAN | D11: : PT UNITED TRACTORS TBK
B13: NO | C13: NAMA MANPOWER | D13: POSISI | E13: LOKASI KERJA
B14: 1 | C14: Haryono | D14: SPV. AC | E14: Non UT HO
B15: 2 | C15: Bambang Agi Siswandi | D15: AC | E15: Non UT HO
B16: 3 | C16: Edi Purwanto | D16: AC | E16: Non UT HO
B17: 4 | C17: Muhammad Ridwan | D17: AC | E17: Non UT HO
B18: 5 | C18: Eko Krisdianto | D18: AC | E18: Non UT HO
B19: 6 | C19: Dwi Riszi Aripyanto | D19: SPV. AC | E19: UT HO & Employee Center
B20: 7 | C20: Hadi Susanto | D20: AC | E20: UT HO & Employee Center
B21: 8 | C21: Joko Santoso | D21: AC | E21: UT HO & Employee Center
B22: 9 | C22: Demig Ali Bimawan | D22: AC | E22: UT HO & Employee Center
B23: 10 | C23: Dimas Solih Prastiaji | D23: AC | E23: UT HO & Employee Center
B24: 11 | C24: Akhmad Taryono | D24: SPV. ME | E24: UT HO & Employee Center
B25: 12 | C25: Bambang Sutrisno | D25: ME | E25: UT HO & Employee Center
... B51: 38 | C51: Bayu Setiawan | D51: Civil | E51: PPI Cakung
