Workbook
Name ______________________xlnm.Print_Area_7: #REF!
Name ______________________xlnm.Print_Area_7: #REF!
Name ______________________xlnm.Print_Area_7: #REF!
Name _____________________xlnm.Print_Area_7: #REF!
Name _____________________xlnm.Print_Area_7: #REF!
Name _____________________xlnm.Print_Area_7: #REF!
Name ____________________xlnm.Print_Area_7: #REF!
Name ____________________xlnm.Print_Area_7: #REF!
Name ____________________xlnm.Print_Area_7: #REF!
Name ___________________xlnm.Print_Area_7: #REF!
Name ___________________xlnm.Print_Area_7: #REF!
Name ___________________xlnm.Print_Area_7: #REF!
Name __________________xlnm.Print_Area_7: #REF!
Name __________________xlnm.Print_Area_7: #REF!
Name __________________xlnm.Print_Area_7: #REF!
Name _________________xlnm.Print_Area_7: #REF!
Name _________________xlnm.Print_Area_7: #REF!
Name _________________xlnm.Print_Area_7: #REF!
Name ________________xlnm.Print_Area_7: #REF!
Name ________________xlnm.Print_Area_7: #REF!
Name _______________xlnm.Print_Area_7: #REF!
Name _______________xlnm.Print_Area_7: #REF!
Name ______________xlnm.Print_Area_7: #REF!
Name ______________xlnm.Print_Area_7: #REF!
Name ______________xlnm.Print_Area_7: #REF!
Name _____________xlnm.Print_Area_7: #REF!
Name _____________xlnm.Print_Area_7: #REF!
Name _____________xlnm.Print_Area_7: #REF!
Name ____________xlnm.Print_Area_7: #REF!
Name ____________xlnm.Print_Area_7: #REF!
Name ___________xlnm.Print_Area_7: #REF!
Name ___________xlnm.Print_Area_7: #REF!
Name __________xlnm.Print_Area_7: #REF!
Name __________xlnm.Print_Area_7: #REF!
Name _________xlnm.Print_Area_7: #REF!
Name _________xlnm.Print_Area_7: #REF!
Name _________xlnm.Print_Area_7: #REF!
Name ________xlnm.Print_Area_7: #REF!
Name ________xlnm.Print_Area_7: #REF!
Name _______xlnm.Print_Area_7: #REF!
Name _______xlnm.Print_Area_7: #REF!
Name ______xlnm.Print_Area_7: #REF!
Name ______xlnm.Print_Area_7: #REF!
Name _____xlnm.Print_Area_7: #REF!
Name _____xlnm.Print_Area_7: #REF!
Name ____xlnm.Print_Area_7: #REF!
Name ____xlnm.Print_Area_7: #REF!
Name ___xlnm.Print_Area_7: #REF!
Name ___xlnm.Print_Area_7: #REF!
Name __xlnm.Print_Area_7: #REF!
Name __xlnm.Print_Area_7: #REF!
Name __xlnm.Print_Area_7: #REF!
Name __xlnm.Print_Area_7: #REF!
Name __xlnm.Print_Area_7: #REF!
Name __xlnm.Print_Area_7: #REF!

Sheet Covering Letter 
F4: Jakarta, 11 Februari 2025
B5: No. | C5: : | D5: CS/0066/2025
B6: Perihal | C6: : | D6: Penawaran Harga Jasa Job Supply Services
B7: Lampiran | C7: : | D7: 4 Lembar
B9: Kepada Yth;
B10: PT United Tractors Tbk
B11: Jl. Raya Bekasi KM 22
B12: Kec. Cakung, Kota Jakarta Timur
B13: Daerah Khusus Ibukota Jakarta 13910
B15: Up | C15: : | D15: Ibu Sara Kirsti Loebis
D16: Corporate Governance & Sustainability Division Head
B19: Dengan hormat,
B20: Sehubungan dengan adanya kebutuhan Penyedia Jasa Tenaga Kerja di perusahaan Bapak/Ibu, bersama ini kami sampaikan penawaran dari PT Mitra Bakti UT sebagai berikut:
B22: - Penyedia Jasa Tenaga Kerja (rincian terlampir)
B23: Rp | D23: =RECAP!G20 -> 1504797000
B25: Note :
B26: 1. Harga belum termasuk PPN 11%
B27: 2. Harga sudah termasuk peralatan dan chemical untuk Cleaning Service, Pest Control, dan Gondola
B28: 3. Harga belum termasuk biaya pembuangan sampah dari TPS
B29: 4. Harga tersebut sudah termasuk BPJS Kesehatan, BPJS Ketenagakerjaan (BPJS Jaminan Kecelakaan Kerja,
B30: BPJS Jaminan Kematian, BPJS Jaminan Hari Tua, BPJS Jaminan Pensiun), Kompensasi Kerja (PP no 35
B31: Tahun 2021), Tunjangan Hari Raya (THR) dan Pakaian Kerja
B32: 5. Harga sudah termasuk biaya MCU, kelebihan biaya MCU ditagihkan sesuai aktual dgn Management Fee 5%
B33: 6. Perhitungan dan aturan lembur sesuai aturan disnaker
B34: 7. Lembur ditagihkan sesuai aktual dengan management fee 5%
B35: 8. Alat Pelindung Diri (APD) ditagihkan sesuai aktual dengan management fee 5%
B36: 9. Makan disediakan oleh User
... B50: Strategic Business & Sales Division Head

Sheet RECAP
B5: Lampiran 1
B6: No. | C6: ='Covering Letter '!D5 -> CS/0066/2025
B8: BIAYA PENYEDIA JASA KEBERSIHAN TAHUN 2025
B9: NAMA | D9: : PT MITRA BAKTI UT
B10: AREA PELAYANAN | D10: : PT UNITED TRACTORS TBK
B12: NO | C12: JOB DESCRIPTION | D12: LUAS AREA (m2) | F12: RATE / m2 | G12: NILAI KONTRAK | J12: NO | K12: JOB DESCRIPTION | L12: LUAS AREA (m2) | N12: RATE / m2 | O12: NILAI KONTRAK | T12: 2024 | U12: 2025 | AD12: MP | AE12: Pek. Tambah | AF12: Tools | AG12: Total
B13: 1 | C13: CLEANING SERVICE | D13: 75087.4 | F13: =G13/D13 -> 12600.544 | G13: =AG21 -> 9.4614209e+08 | J13: 1 | K13: CLEANING SERVICE | L13: 75087.4 | N13: =O13/L13 -> 12600.544 | O13: =AG21 -> 9.4614209e+08 | T13: 1034431000 | U13: =G13 -> 9.4614209e+08 | V13: =U13-T13 -> -88288913 | X13: =V13/T13 -> -0.08535022 | Y13: UMK dan Inflasi | AD13: ='SC HO'!F42+'SC HO'!G42+'SC HO'!H42 -> 765899800 | AE13: 0 | AF13: ='TOOLS RECAP'!G152 -> 1.0309267e+08 | AG13: =SUM(AD13:AF13) -> 8.6899247e+08
B14: 2 | C14: OFFICE BOY | D14: 10888 | F14: =G14/D14 -> 11120.5 | G14: =AG22 -> 121080000 | J14: 2 | K14: OFFICE BOY | L14: 10888 | N14: =O14/L14 -> 11120.5 | O14: =AG22 -> 121080000 | T14: 127646000 | U14: =G14 -> 121080000 | V14: =U14-T14 -> -6566000 | X14: =V14/T14 -> -0.051439136 | Y14: UMK, Inflasi, Tambahan 1 MP OB lt 9 | AD14: ='SC HO'!I42 -> 121080000 | AE14: 0 | AF14: 0 | AG14: =SUM(AD14:AF14) -> 121080000
B15: 3 | C15: CLEANING AREA OUTDOOR | D15: 317937 | F15: =G15/D15 -> 982.91532 | G15: =AG23 -> 3.1250515e+08 | J15: 3 | K15: CLEANING AREA OUTDOOR | L15: 317937 | N15: =O15/L15 -> 982.91532 | O15: =AG23 -> 3.1250515e+08 | T15: 280908000 | U15: =G15 -> 3.1250515e+08 | V15: =U15-T15 -> 31597147 | X15: =V15/T15 -> 0.11248219 | Y15: Peralatan Gardener oleh MBUT | AD15: ='SC HO'!J42+'SC HO'!K42 -> 267446000 | AE15: 0 | AF15: ='TOOLS RECAP'!G171 -> 39794064 | AG15: =SUM(AD15:AF15) -> 3.0724006e+08
B16: 4 | C16: PEST CONTROL | D16: 0 | F16: Ls | G16: =AG24 -> 39453560 | J16: 4 | K16: PEST CONTROL | L16: 0 | N16: Ls | O16: =AG24 -> 39453560 | T16: 51732000 | U16: =G16 -> 39453560 | V16: =U16-T16 -> -12278440 | X16: =V16/T16 -> -0.2373471 | Y16: UMK dan Inflasi | AD16: ='SC HO'!L42 -> 32704000 | AE16: 0 | AF16: ='TOOLS RECAP'!G188 -> 14496474 | AG16: =SUM(AD16:AF16) -> 47200474
B17: 5 | C17: GONDOLA | D17: 58275 | F17: =G17/D17 -> 1469.1635 | G17: =AG25 -> 85615503 | J17: 5 | K17: GONDOLA | L17: 58275 | N17: =O17/L17 -> 1469.1635 | O17: =AG25 -> 85615503 | T17: 93283000 | U17: =G17 -> 85615503 | V17: =U17-T17 -> -7667496.5 | X17: =V17/T17 -> -0.082196075 | Y17: Selisih Tambahan 1 MP | AD17: ='SC HO'!M42+'SC HO'!N42 -> 81311800 | AE17: 0 | AF17: ='TOOLS RECAP'!G219 -> 3270292 | AG17: =SUM(AD17:AF17) -> 84582092
AF18: =SUM(AF13:AF17) -> 1.606535e+08
B19: TOTAL | G19: =SUM(G13:G17) -> 1.5047963e+09 | J19: TOTAL | O19: =SUM(O13:O17) -> 1.5047963e+09 | T19: =SUM(T13:T17) -> 1588000000 | U19: =SUM(U13:U17) -> 1.5047963e+09 | V19: =U19-T19 -> -83203703 | X19: =V19/T19 -> -0.052395279
B20: PEMBULATAN | G20: =ROUNDUP(G19,-3) -> 1504797000 | J20: PEMBULATAN | O20: =ROUNDUP(O19,-3) -> 1504797000 | AD20: MP | AE20: Pek. Tambah | AF20: Tools | AG20: Total
B21: Note : | X21: JUMLAH MP | AD21: =AD13 -> 765899800 | AE21: 0 | AF21: ='TOOLS RECAP (2)'!K122 -> 1.8024229e+08 | AG21: =SUM(AD21:AF21) -> 9.4614209e+08
B22: 1. Harga belum termasuk PPN 11% | T22: =G13/X22 -> 11680767 | X22: 81 | AD22: =AD14 -> 121080000 | AE22: 0 | AF22: 0 | AG22: =SUM(AD22:AF22) -> 121080000
B23: 2. Harga sudah termasuk peralatan dan chemical untuk Cleaning Service, Pest Control, dan Gondola | T23: =G14/X23 -> 8072000 | X23: 15 | AD23: =AD15 -> 267446000 | AE23: 0 | AF23: ='TOOLS RECAP (2)'!K141 -> 45059147 | AG23: =SUM(AD23:AF23) -> 3.1250515e+08
B24: 3. Harga belum termasuk biaya pembuangan sampah dari TPS | T24: =G15/X24 -> 9765785.8 | X24: 32 | AD24: =AD16 -> 32704000 | AE24: 0 | AF24: ='TOOLS RECAP (2)'!K157 -> 6749560 | AG24: =SUM(AD24:AF24) -> 39453560
B25: 4. Harga tersebut sudah termasuk BPJS Kesehatan, BPJS Ketenagakerjaan (BPJS Jaminan Kecelakaan Kerja, BPJS Jaminan Kematian | T25: =G16/X25 -> 9863390 | U25: =T17+T25 -> 103146390 | V25: =G17-U25 -> -17530887 | X25: 4 | AD25: =AD17 -> 81311800 | AE25: 0 | AF25: ='TOOLS RECAP (2)'!K179 -> 4303703.5 | AG25: =SUM(AD25:AF25) -> 85615503
B26: BPJS Jaminan Hari Tua, BPJS Jaminan Pensiun), Kompensasi Kerja (PP no 35 Tahun 2021), Tunjangan Hari Raya (THR)
B27: dan Pakaian Kerja | J27: Cost | K27: ='SC HO'!O60 -> 1.1084603e+09 | L27: ='SC HO'!N60 -> 0
B28: 5. Harga sudah termasuk biaya MCU, kelebihan biaya MCU ditagihkan sesuai aktual dgn Management Fee 5% | K28: ='TOOLS RECAP (2)'!M180 -> 2.1821259e+08
B29: 6. Perhitungan dan aturan lembur sesuai aturan disnaker | K29: =K27+K28 -> 1.3266729e+09 | L29: =G20-K29 -> 1.7812411e+08 | N29: =L29/G20 -> 0.11837085
B30: 7. Lembur ditagihkan sesuai aktual dengan management fee 5%
B31: 8. Alat Pelindung Diri (APD) ditagihkan sesuai aktual dengan management fee 5%
B32: 9. Makan disediakan oleh User
B33: 10. Training ditagihkan sesuai aktual dengan management fee 5%
B34: 11. Apresiasi akhir tahun tidak termasuk dalam harga, dan akan ditagihkan sesuai aktual dengan Cost of Fund sebesar 3%
B35: 12. Harga akan disesuaikan setiap tahun berdasarkan kenaikan upah minimum kabupaten/kota (UMK)
T38: OH | U38: ='SC HO'!O59 -> 1.5998129e+08
B39: Hormat Kami, | F39: Menyetujui, | T39: Fee | U39: ='SC HO'!O60 -> 1.1084603e+09
B40: PT Mitra Bakti UT | F40: ='Covering Letter '!B10 -> PT United Tractors Tbk | T40: Tools | U40: ='TOOLS RECAP'!K154 -> 9347730.1
U41: =SUM(U38:U40) -> 1.2777893e+09
U42: =U41/G20 -> 0.84914399
B46: ='Covering Letter '!B49 -> Sandy Yudha S | F46: =RIGHT('Covering Letter '!D15,18) -> Sara Kirsti Loebis
B47: ='Covering Letter '!B50 -> Strategic Business & Sales Division Head | F47: ='Covering Letter '!D16 -> Corporate Governance & Sustainability Division Head

Sheet SC HO
B5: Lampiran 2
B6: No. | C6: ='Covering Letter '!D5 -> CS/0066/2025
B8: STRUKTUR BIAYA JASA TENAGA KERJA
B9: TAHUN 2025
B10: AREA DKI JAKARTA | P10: =SUM(P11:P14) -> 1.5283593e+09
P11: =7500000*141 -> 1057500000
B12: NO | C12: URAIAN | F12: CLEANING SERVICE | I12: OFFICE BOY | J12: CLEANING AREA OUTDOR | L12: PEST CONTROL | M12: GONDOLA | O12: KETERANGAN | P12: =3000*N20 -> 93585434
F13: KOORDINATOR | G13: SUPERVISOR | H13: CREW | I13: CREW | J13: SUPERVISOR | K13: CREW | L13: CREW | M13: SUPERVISOR | N13: CREW | P13: =1500000*141 -> 211500000
B14: I | C14: FIXED COST | F14: =SUM(F15:F18) -> 6848848.2 | G14: =SUM(G15:G18) -> 6848848.2 | H14: =SUM(H15:H18) -> 6848848.2 | I14: =SUM(I15:I18) -> 6848848.2 | J14: =SUM(J15:J18) -> 6848848.2 | K14: =SUM(K15:K18) -> 6848848.2 | L14: =SUM(L15:L18) -> 6848848.2 | M14: =SUM(M15:M18) -> 6848848.2 | N14: =SUM(N15:N18) -> 6848848.2 | P14: 1.6577391e+08
A15: ok | B15: 1 | C15: Upah | F15: =5396760 -> 5396760 | G15: =5396760 -> 5396760 | H15: =5396760 -> 5396760 | I15: =5396760 -> 5396760 | J15: =5396760 -> 5396760 | K15: =5396760 -> 5396760 | L15: =5396760 -> 5396760 | M15: =5396760 -> 5396760 | N15: =5396760 -> 5396760 | O15: Upah Tenaga Kerja (UMK 2025) | P15: 5067381 | Q15: 5396760
A16: ok | B16: 2 | C16: BPJS | E16: 0.1024 | F16: =F15*$E$16 -> 552628.22 | G16: =G15*$E$16 -> 552628.22 | H16: =H15*$E$16 -> 552628.22 | I16: =I15*$E$16 -> 552628.22 | J16: =J15*$E$16 -> 552628.22 | K16: =K15*$E$16 -> 552628.22 | L16: =L15*$E$16 -> 552628.22 | M16: =M15*$E$16 -> 552628.22 | N16: =N15*$E$16 -> 552628.22 | O16: Mengikuti Regulasi Pemerintah (JHT, JKK, JK)
A17: ok | B17: 3 | C17: THR | F17: =F15/12 -> 449730 | G17: =G15/12 -> 449730 | H17: =H15/12 -> 449730 | I17: =I15/12 -> 449730 | J17: =J15/12 -> 449730 | K17: =K15/12 -> 449730 | L17: =L15/12 -> 449730 | M17: =M15/12 -> 449730 | N17: =N15/12 -> 449730 | O17: Upah /12
A18: ok | B18: 4 | C18: Kompensasi Akhir Kontrak (UUCK) | F18: =F15/12 -> 449730 | G18: =G15/12 -> 449730 | H18: =H15/12 -> 449730 | I18: =I15/12 -> 449730 | J18: =J15/12 -> 449730 | K18: =K15/12 -> 449730 | L18: =L15/12 -> 449730 | M18: =M15/12 -> 449730 | N18: =N15/12 -> 449730 | O18: Upah /12
B19: II | C19: OVERTIME | F19: =F22 -> 0 | G19: =G22 -> 0 | H19: =H22 -> 0 | I19: =I22 -> 0 | J19: =J22 -> 0 | K19: =K22 -> 0 | L19: =L22 -> 0 | M19: =M22 -> 0 | N19: =N22 -> 0
A20: not ok | B20: 1 | C20: TUL | F20: =SUM(F15/173) -> 31195.145 | G20: =SUM(G15/173) -> 31195.145 | H20: =SUM(H15/173) -> 31195.145 | I20: =SUM(I15/173) -> 31195.145 | J20: =SUM(J15/173) -> 31195.145 | K20: =SUM(K15/173) -> 31195.145 | L20: =SUM(L15/173) -> 31195.145 | M20: =SUM(M15/173) -> 31195.145 | N20: =SUM(N15/173) -> 31195.145 | O20: Upah /173
A21: not ok | B21: 2 | C21: Jam Lembur | F21: 0 | G21: 0 | H21: 0 | I21: 0 | J21: 0 | K21: 0 | L21: 0 | M21: 0 | N21: 0 | O21: Sesuai Aktual Dilapangan
A22: not ok | B22: 3 | C22: Upah Lembur | F22: =F20*F21 -> 0 | G22: =G20*G21 -> 0 | H22: =H20*H21 -> 0 | I22: =I20*I21 -> 0 | J22: =J20*J21 -> 0 | K22: =K20*K21 -> 0 | L22: =L20*L21 -> 0 | M22: =M20*M21 -> 0 | N22: =N20*N21 -> 0 | O22: Ditagihkan Sesuai Aktual Dengan Management Fee 5% | P22: =SUM(P17:P21) -> 0
B23: III | C23: VARIABLE COST | F23: =SUM(F24:F31) -> 2778333.3 | G23: =SUM(G24:G31) -> 1778333.3 | H23: =SUM(H24:H31) -> 736666.67 | I23: =SUM(I24:I31) -> 695000 | J23: =SUM(J24:J31) -> 1695000 | K23: =SUM(K24:K31) -> 695000 | L23: =SUM(L24:L31) -> 792222.22 | M23: =SUM(M24:M31) -> 2570000 | N23: =SUM(N24:N31) -> 1472777.8
A24: ok | B24: 1 | C24: Medical Checkup | F24: 60000 | G24: 60000 | H24: 60000 | I24: 60000 | J24: 60000 | K24: 60000 | L24: 60000 | M24: 60000 | N24: 60000 | O24: Kelebihan biaya MCU ditagihkan sesuai aktual | P24: =682000/12 -> 56833.333
A25: ok, (+) item | B25: 2 | C25: Seragam | F25: 135000 | G25: 135000 | H25: 135000 | I25: 135000 | J25: 135000 | K25: 135000 | L25: 135000 | M25: 135000 | N25: 135000 | O25: 3xBaju, 3xCelana, Polo Shirt, Sabuk, Sepatu | P25: Kemeja | Q25: 110000 | R25: =Q25*3 -> 330000
A26: not ok | B26: 3 | C26: APD | F26: 0 | G26: 0 | H26: 0 | I26: 0 | J26: 0 | K26: 0 | L26: 0 | M26: 0 | N26: 0 | O26: Ditagihkan Sesuai Aktual Dengan Management Fee 5% | P26: Celana | Q26: 130000 | R26: =Q26*3 -> 390000
A27: ok | B27: 4 | C27: Uang Makan | F27: 0 | G27: 0 | H27: 0 | I27: 0 | J27: 0 | K27: 0 | L27: 0 | M27: 0 | N27: 0 | O27: Disediakan oleh User | P27: Kaos Polo | Q27: 95000 | R27: =Q27*1 -> 95000
A28: ok | B28: 5 | C28: Sertifikasi | F28: =3000000/36 -> 83333.333 | G28: =3000000/36 -> 83333.333 | H28: =1500000/36 -> 41666.667 | I28: 0 | J28: 0 | K28: 0 | L28: =3500000/36 -> 97222.222 | M28: =(9000000+4500000)/36 -> 375000 | N28: =(5500000+4500000)/36 -> 277777.78 | P28: Sabuk | Q28: 20000 | R28: =Q28 -> 20000
A29: not ok | B29: 6 | C29: Training | F29: 0 | G29: 0 | H29: 0 | I29: 0 | J29: 0 | K29: 0 | L29: 0 | M29: 0 | N29: 0 | O29: Ditagihkan Sesuai Aktual Dengan Management Fee 5% | P29: Sepatu | Q29: 150000 | R29: =Q29 -> 150000
A30: ok | B30: 7 | C30: Tunjangan Jabatan | F30: 2000000 | G30: 1000000 | J30: 1000000 | M30: =1000000+500000 -> 1500000 | N30: 500000 | R30: =SUM(R25:R29) -> 985000
A31: ok | B31: 8 | C31: Overhead Expenses | F31: =SUM(F32:F35) -> 500000 | G31: =SUM(G32:G35) -> 500000 | H31: =SUM(H32:H35) -> 500000 | I31: =SUM(I32:I35) -> 500000 | J31: =SUM(J32:J35) -> 500000 | K31: =SUM(K32:K35) -> 500000 | L31: =SUM(L32:L35) -> 500000 | M31: =SUM(M32:M35) -> 500000 | N31: =SUM(N32:N35) -> 500000
C32: Biaya Sambung Rasa | F32: 155000 | G32: 155000 | H32: 155000 | I32: 155000 | J32: 155000 | K32: 155000 | L32: 155000 | M32: 155000 | N32: 155000
C33: Biaya Recruitment | F33: 50000 | G33: 50000 | H33: 50000 | I33: 50000 | J33: 50000 | K33: 50000 | L33: 50000 | M33: 50000 | N33: 50000
C34: Biaya Suka Duka | F34: 45000 | G34: 45000 | H34: 45000 | I34: 45000 | J34: 45000 | K34: 45000 | L34: 45000 | M34: 45000 | N34: 45000
C35: Biaya Operational Support | F35: 250000 | G35: 250000 | H35: 250000 | I35: 250000 | J35: 250000 | K35: 250000 | L35: 250000 | M35: 250000 | N35: 250000
C36: TOTAL I + II + III | F36: =F14+F19+F23 -> 9627181.6 | G36: =G14+G19+G23 -> 8627181.6 | H36: =H14+H19+H23 -> 7585514.9 | I36: =I14+I19+I23 -> 7543848.2 | J36: =J14+J19+J23 -> 8543848.2 | K36: =K14+K19+K23 -> 7543848.2 | L36: =L14+L19+L23 -> 7641070.4 | M36: =M14+M19+M23 -> 9418848.2 | N36: =N14+N19+N23 -> 8321626
C37: MANAGEMENT FEE | E37: 0.07 | F37: =F36*$E$37 -> 673902.71 | G37: =G36*$E$37 -> 603902.71 | H37: =H36*$E$37 -> 530986.04 | I37: =I36*$E$37 -> 528069.38 | J37: =J36*$E$37 -> 598069.38 | K37: =K36*$E$37 -> 528069.38 | L37: =L36*$E$37 -> 534874.93 | M37: =M36*$E$37 -> 659319.38 | N37: =N36*$E$37 -> 582513.82 | O37: 7% dari Total Cost
C38: SUB TOTAL | F38: =F36+F37 -> 10301084 | G38: =G36+G37 -> 9231084.3 | H38: =H36+H37 -> 8116500.9 | I38: =I36+I37 -> 8071917.6 | J38: =J36+J37 -> 9141917.6 | K38: =K36+K37 -> 8071917.6 | L38: =L36+L37 -> 8175945.4 | M38: =M36+M37 -> 10078168 | N38: =N36+N37 -> 8904139.8
C39: PEMBULATAN | F39: =ROUNDUP(F38,-2) -> 10301100 | G39: =ROUNDUP(G38,-2) -> 9231100 | H39: =ROUNDUP(H38,-2) -> 8116600 | I39: =ROUNDUP(I38,-2) -> 8072000 | J39: =ROUNDUP(J38,-2) -> 9142000 | K39: =ROUNDUP(K38,-2) -> 8072000 | L39: =ROUNDUP(L38,-2) -> 8176000 | M39: =ROUNDUP(M38,-2) -> 10078200 | N39: =ROUNDUP(N38,-2) -> 8904200
C41: JUMLAH MANPOWER | F41: 2 | G41: 6 | H41: =77+3+5 -> 85 | I41: 15 | J41: 1 | K41: 32 | L41: 4 | M41: 1 | N41: 8 | O41: =SUM(F41:N41) -> 154
C42: TOTAL BIAYA MANPOWER | F42: =F39*F41 -> 20602200 | G42: =G39*G41 -> 55386600 | H42: =H39*H41 -> 689911000 | I42: =I39*I41 -> 121080000 | J42: =J39*J41 -> 9142000 | K42: =K39*K41 -> 258304000 | L42: =L39*L41 -> 32704000 | M42: =M39*M41 -> 10078200 | N42: =N39*N41 -> 71233600 | O42: =SUM(F42:N42) -> 1268441600
P43: =O42+'TOOLS RECAP'!G152+'TOOLS RECAP'!G171+'TOOLS RECAP'!G188+'TOOLS RECAP'!G219 -> 1.4290951e+09
H44: 73
H45: =H44+3 -> 76
H46: =H45+5 -> 81
B47: Hormat Kami, | O47: Menyetujui,
B48: ='Covering Letter '!B44 -> PT Mitra Bakti UT | O48: ='Covering Letter '!B10 -> PT United Tractors Tbk
B54: ='Covering Letter '!B49 -> Sandy Yudha S | O54: =RIGHT('Covering Letter '!D15,18) -> Sara Kirsti Loebis
B55: Strategic Business & Sales Division Head | O55: ='Covering Letter '!D16 -> Corporate Governance & Sustainability Division Head
E57: OH | F57: =F31*F41 -> 1000000 | G57: =G31*G41 -> 3000000 | H57: =H31*H41 -> 42500000 | I57: =I31*I41 -> 7500000 | J57: =J31*J41 -> 500000 | K57: =K31*K41 -> 16000000 | L57: =L31*L41 -> 2000000 | M57: =M31*M41 -> 500000 | N57: =N31*N41 -> 4000000 | O57: =SUM(F57:N57) -> 77000000
E58: M fee | F58: =F37*F41 -> 1347805.4 | G58: =G37*G41 -> 3623416.3 | H58: =H37*H41 -> 45133814 | I58: =I37*I41 -> 7921040.6 | J58: =J37*J41 -> 598069.38 | K58: =K37*K41 -> 16898220 | L58: =L37*L41 -> 2139499.7 | M58: =M37*M41 -> 659319.38 | N58: =N37*N41 -> 4660110.6 | O58: =SUM(F58:N58) -> 82981295
O59: =SUM(O57:O58) -> 1.5998129e+08
O60: =O42-O59 -> 1.1084603e+09 | T60: =O59/O42 -> 0.12612429
O62: =O61/O42 -> 0

Sheet TOOLS RECAP
B5: Lampiran 2
B6: No. | C6: ='Covering Letter '!D5 -> CS/0066/2025
B8: A. PERALATAN CLEANING
B9: No | C9: Keterangan | D9: Kuantitas | F9: Harga | G9: Harga | H9: Depr | I9: Remarks
B10: 1 | C10: Mesin Polisher | D10: 4 | E10: bh | F10: by UT | G10: 0 | H10: 0 | I10: by UT
B11: 2 | C11: Mesin Vacuum 60 L | D11: 8 | E11: bh | F11: by UT | G11: 0 | H11: 0 | I11: by UT
B12: 3 | C12: Extractor Sofa Bed | D12: 2 | E12: bh | F12: by UT | G12: 0 | H12: 0 | I12: by UT
B13: 4 | C13: Hand Polisher | D13: 2 | E13: bh | F13: by UT | G13: 0 | H13: 0 | I13: by UT
B14: 5 | C14: Blower | D14: 12 | E14: bh | F14: by UT | G14: 0 | H14: 0 | I14: by UT
B15: 6 | C15: Janitor Cart | D15: 12 | E15: bh | F15: by UT | G15: 0 | H15: 0 | I15: by UT
B16: 7 | C16: Air Deodorizer Glade Liquid Ocean Escape 4L | D16: 36 | E16: bh | F16: 445944.96 | G16: =F16*107% -> 477161.11 | H16: 12
B17: 8 | C17: Body Bag | D17: 60 | E17: bh | F17: 397800 | G17: =F17*107% -> 425646 | H17: 12
B18: 9 | C18: Botol Sprayer | D18: 60 | E18: bh | F18: 153000 | G18: =F18*107% -> 163710 | H18: 12
B19: 10 | C19: Bucket - Double 2X2,5L | D19: 12 | E19: bh | F19: 1235677 | G19: =F19*107% -> 1322174.3 | H19: 12
B20: 11 | C20: Cady Cary | D20: 12 | E20: bh | F20: 93600 | G20: =F20*107% -> 100152 | H20: 12
B21: 12 | C21: Carpet Care Refresh 4L | D21: 36 | E21: bh | F21: 821793.6 | G21: =F21*107% -> 879319.15 | H21: 12
B22: 13 | C22: Carpet Care Rugbee Hdssr 4L | D22: 24 | E22: bh | F22: 820719.36 | G22: =F22*107% -> 878169.72 | H22: 12
B23: 14 | C23: Carpet Care Rugbee Shampoo 4L | D23: 36 | E23: bh | F23: 625613.76 | G23: =F23*107% -> 669406.72 | H23: 12
B24: 15 | C24: Dust Bin 120L | D24: 12 | E24: bh | F24: 1152000 | G24: =F24*107% -> 1232640 | H24: 12
B25: 16 | C25: Dustpan + Nyloon Broom | D25: 48 | E25: bh | F25: 402531.84 | G25: =F25*107% -> 430709.07 | H25: 12
B26: 17 | C26: Dustpan Besar | D26: 48 | E26: bh | F26: 207527.04 | G26: =F26*107% -> 222053.93 | H26: 12
B27: 18 | C27: Dustpan Kecil | D27: 24 | E27: bh | F27: 82995.84 | G27: =F27*107% -> 88805.549 | H27: 12
... B68: 59 | C68: Nyloon Broom | D68: 36 | E68: bh | F68: 112320 | G68: =F68*107% -> 120182.4 | H68: 12
B69: 60 | C69: Obat Nyamuk Spray Baygon 600Ml | D69: 60 | E69: bh | F69: 0 | G69: =F69*107% -> 0 | H69: 12 | I69: by UT
B70: 61 | C70: Obat Nyamuk Spray Hit 600Ml | D70: 60 | E70: bh | F70: 0 | G70: =F70*107% -> 0 | H70: 12 | I70: by UT
B71: 62 | C71: Obat Rayap Premise | D71: 60 | E71: bh | F71: 0 | G71: =F71*107% -> 0 | H71: 12 | I71: by UT
B72: 63 | C72: Pad Coklat 17 Inch | D72: 24 | E72: bh | F72: 300974.4 | G72: =F72*107% -> 322042.61 | H72: 12
B73: 64 | C73: Pad Hitam 17 Inch | D73: 24 | E73: bh | F73: 282162.24 | G73: =F73*107% -> 301913.6 | H73: 12
B74: 65 | C74: Pad Merah 17 Inch | D74: 96 | E74: bh | F74: 1166400 | G74: =F74*107% -> 1248048 | H74: 12
B75: 66 | C75: Pad Merah 20 Inch | D75: 36 | E75: bh | F75: 790560 | G75: =F75*107% -> 845899.2 | H75: 12
B76: 67 | C76: Pad Putih 17 Inch | D76: 72 | E76: bh | F76: 874800 | G76: =F76*107% -> 936036 | H76: 12
B77: 68 | C77: Pad Putih 20 Inch | D77: 24 | E77: bh | F77: 342720 | G77: =F77*107% -> 366710.4 | H77: 12
B78: 69 | C78: Pembersih Kaca Glance Glass Cleaner 4L | D78: 84 | E78: bh | F78: 522617.76 | G78: =F78*107% -> 559201 | H78: 12
B79: 70 | C79: Pembersih Kaca Strip Powder | D79: 84 | E79: bh | F79: 252000 | G79: =F79*107% -> 269640 | H79: 12
B80: 71 | C80: Pembersih Lantai Brite Plus 4L | D80: 84 | E80: bh | F80: 621321.12 | G80: =F80*107% -> 664813.6 | H80: 12
B81: 72 | C81: Pembersih Lantai Dust Way | D81: 36 | E81: bh | F81: 788110.56 | G81: =F81*107% -> 843278.3 | H81: 12
B82: 73 | C82: Pembersih Lantai Floor Clean 4L | D82: 84 | E82: bh | F82: 510814.08 | G82: =F82*107% -> 546571.07 | H82: 12
B83: 74 | C83: Pembersih Lantai Forward 4L | D83: 72 | E83: bh | F83: 738815.04 | G83: =F83*107% -> 790532.09 | H83: 12
... B144: 135 | C144: Pengharum Ruangan Calmic, Ecocare & Scenting | D144: 30 | E144: titik | F144: 35200000 | G144: =F144*107% -> 37664000 | H144: 12
B145: 136 | C145: Pembersih Lantai Super Pell 770Ml | D145: 24 | E145: bh | F145: 60480 | G145: =F145*107% -> 64713.6 | H145: 12 | I145: Peruntukan Sukapura & Jababeka
B146: 137 | C146: Pembersih Toilet Terrific 4L | D146: 36 | E146: bh | F146: 204327.36 | G146: =F146*107% -> 218630.28 | H146: 12 | I146: Peruntukan Sukapura & Jababeka
B147: 138 | C147: Pengharum Gantung Dahlia 70Gr | D147: 12 | E147: bh | F147: 23040 | G147: =F147*107% -> 24652.8 | H147: 12 | I147: Peruntukan Sukapura & Jababeka
B148: 139 | C148: Pengharum Gantung Glade 70Gr | D148: 12 | E148: bh | F148: 21600 | G148: =F148*107% -> 23112 | H148: 12 | I148: Peruntukan Sukapura & Jababeka
B149: 140 | C149: Pengharum Gantung Stella | D149: 12 | E149: bh | F149: 18000 | G149: =F149*107% -> 19260 | H149: 12 | I149: Peruntukan Sukapura & Jababeka
B150: 141 | C150: Pengharum Ruangan Spray Glade Refill Matic 225Ml | D150: 24 | E150: bh | F150: 129600 | G150: =F150*107% -> 138672 | H150: 12 | I150: Peruntukan Sukapura & Jababeka
B151: 142 | C151: Pengharum Ruangan Spray Stella 400Ml | D151: 36 | E151: bh | F151: 151200 | G151: =F151*107% -> 161784 | H151: 12 | I151: Peruntukan Sukapura & Jababeka
F152: =SUM(F10:F151) -> 96348287 | G152: =SUM(G10:G151) -> 1.0309267e+08 | K152: =G152+G171+G188+G219 -> 1.606535e+08
K153: =F152+F171+G188+G219 -> 1.5130577e+08
B154: B. PERALATAN GARDENER | K154: =K152-K153 -> 9347730.1
B155: No | C155: Keterangan | D155: Kuantitas | F155: Harga | H155: Depr | I155: Remarks
B156: 1 | C156: Mesin Potong Rumput | D156: 1 | E156: bh | F156: 400000 | G156: =F156*107% -> 428000 | H156: 12
B157: 2 | C157: Mesin Potong Pohon | D157: 1 | E157: bh | F157: 0 | G157: =F157*107% -> 0 | H157: 12 | I157: by UT
B158: 3 | C158: Mesin Jet Steamer | D158: 2 | E158: bh | F158: 0 | G158: =F158*107% -> 0 | H158: 12 | I158: by UT
B159: 4 | C159: Dustpan Besar | D159: 12 | E159: bh | F159: 0 | G159: =F159*107% -> 0 | H159: 12
B160: 5 | C160: Dustpan Kecil | D160: 4 | E160: bh | F160: 0 | G160: =F160*107% -> 0 | H160: 12
B161: 6 | C161: Masker Kain | D161: 66 | E161: bh | F161: 0 | G161: =F161*107% -> 0 | H161: 12
B162: 7 | C162: Nyloon Broom | D162: 12 | E162: bh | F162: 0 | G162: =F162*107% -> 0 | H162: 12
B163: 8 | C163: Plastik Sampah Hitam 100X120 | D163: 50 | E163: bh | F163: 0 | G163: =F163*107% -> 0 | H163: 12
B164: 9 | C164: Plastik Sampah Hitam 80X100 | D164: 6 | E164: bh | F164: 0 | G164: =F164*107% -> 0 | H164: 12
B165: 10 | C165: Plastik Sampah Hitam 90X120 | D165: 10 | E165: bh | F165: 0 | G165: =F165*107% -> 0 | H165: 12
B166: 11 | C166: Plastik Sampah Merah 80X100 | D166: 8 | E166: bh | F166: 0 | G166: =F166*107% -> 0 | H166: 12
B167: 12 | C167: Sarung Tangan Kain | D167: 360 | E167: bh | F167: 720000 | G167: =F167*107% -> 770400 | H167: 12
B168: 13 | C168: Sarung Tangan Karet | D168: 22 | E168: bh | F168: 48314.2 | G168: =F168*107% -> 51696.194 | H168: 12
B169: 14 | C169: Sapu Lidi Gagang Panjang | D169: 8 | E169: bh | F169: 22400 | G169: =F169*107% -> 23968 | H169: 12
B170: 15 | C170: Sewa Bonsai & Tanaman Hias | D170: 12 | E170: bh | F170: 36000000 | G170: =F170*107% -> 38520000 | H170: 12
F171: =SUM(F156:F170) -> 37190714 | G171: =SUM(G156:G170) -> 39794064
B173: C. PEST CONTROL
B174: No | C174: Keterangan | D174: Kuantitas | F174: Harga | G174: Harga | H174: Depr | I174: Remarks
B175: 1 | C175: Lem Tikus | D175: 690 | E175: bh | G175: 1193479.2 | H175: 0 | I175: by UT
B176: 2 | C176: Obat Fogging Cynof | D176: 153 | E176: bh | G176: 2067556.3 | H176: 0 | I176: by UT
B177: 3 | C177: Obat Fogging Nuvet | D177: 185 | E177: bh | G177: 3199996.8 | H177: 0 | I177: by UT
B178: 4 | C178: Obat Lalat Flygard | D178: 16 | E178: bh | G178: 951350.4 | H178: 0 | I178: by UT
B179: 5 | C179: Obat Nyamuk Spray Baygon 600Ml | D179: 62 | E179: bh | G179: 297600 | H179: 0 | I179: by UT
B180: 6 | C180: Obat Nyamuk Spray Hit 600Ml | D180: 57 | E180: bh | G180: 259920 | H180: 0 | I180: by UT
B181: 7 | C181: Obat Rayap Premise | D181: 34 | E181: bh | G181: 1212971.8 | H181: 12
B182: 8 | C182: Obat Serangga Spa Insecticide | D182: 144 | E182: bh | G182: 1209600 | H182: 12
B183: 9 | C183: Racun Tikus Contract | D183: 120 | E183: bh | G183: 600000 | H183: 12
B184: 10 | C184: Sarung Tangan Kain | D184: 96 | E184: bh | G184: 192000 | H184: 12
B185: 11 | C185: Solar | D185: 1440 | E185: bh | G185: 2304000 | H185: 12
B186: 12 | C186: Bensin | D186: 720 | E186: bh | G186: 1008000 | H186: 12
B187: 13 | C187: Gerobak Dan Perangkap | D187: 0 | E187: bh | G187: 0 | H187: 12 | I187: Add Cost
F188: =SUM(F175:F187) -> 0 | G188: =SUM(G175:G187) -> 14496474
B190: D. GONDOLA
B191: No | C191: Keterangan | D191: Kuantitas | F191: Harga | G191: Harga | H191: Depr | I191: Remarks
B192: 1 | C192: Floor Squeegee | D192: 12 | E192: bh | G192: 36000 | H192: 12
B193: 2 | C193: Hand Soap 20L | D193: 18 | E193: bh | G193: 481680 | H193: 12
B194: 3 | C194: Kanebo | D194: 32 | E194: bh | G194: 111360 | H194: 12
B195: 4 | C195: Karet Squeegee 1M | D195: 95 | E195: bh | G195: 362573.01 | H195: 12
B196: 5 | C196: Lap Microfiber Biru | D196: 100 | E196: bh | G196: 211860.8 | H196: 12
B197: 6 | C197: Mop Set | D197: 1 | E197: bh | G197: 9946.08 | H197: 12
B198: 7 | C198: Neutral Cleaner Marble Klin 4L | D198: 5 | E198: bh | G198: 61601.4 | H198: 12
B199: 8 | C199: Pembersih Kaca Glance Glass Cleaner 4L | D199: 58 | E199: bh | G199: 360855.12 | H199: 12
B200: 9 | C200: Pembersih Kaca Strip Powder | D200: 50 | E200: bh | G200: 150000 | H200: 12
B201: 10 | C201: Plastik Sampah Hijau 40X60 | D201: 8 | E201: bh | G201: 18240 | H201: 12
B202: 11 | C202: Plastik Sampah Hitam 60X80 | D202: 8 | E202: bh | G202: 14400 | H202: 12
B203: 12 | C203: Plastik Sampah Hitam 90X120 | D203: 76 | E203: bh | G203: 127680 | H203: 12
... B212: 21 | C212: Window Washer 35 Inch | D212: 27 | E212: bh | G212: 116027.64 | H212: 12
B213: 22 | C213: Carbiner | D213: 25 | E213: bh | G213: 0 | H213: 0 | I213: Add Cost
B214: 23 | C214: Body Harness | D214: 4 | E214: bh | G214: 0 | H214: 0 | I214: Add Cost
B215: 24 | C215: Carmantel | D215: 1 | E215: bh | G215: 0 | H215: 0 | I215: Add Cost
...

Sheet TOOLS RECAP (2)
B4: Lampiran 2
B5: No. | D5: ='Covering Letter '!D5 -> CS/0066/2025
B7: A. PERALATAN CLEANING
B8: No | C8: Keterangan | D8: Keterangan | E8: Kuantitas | G8: Kuantitas | I8: Unit Price | J8: Depr | K8: Total | L8: Remarks
B9: 1 | C9: Mesin Polisher | D9: Mesin Polisher | E9: 4 | F9: bh | I9: 0 | J9: 0 | K9: 0 | L9: by UT
B10: 2 | C10: Mesin Vacuum 60 L | D10: Mesin Vacuum 60 L | E10: 8 | F10: bh | I10: 0 | J10: 0 | K10: 0 | L10: by UT
B11: 3 | C11: Extractor Sofa Bed | D11: Extractor Sofa Bed | E11: 2 | F11: bh | I11: 0 | J11: 0 | K11: 0 | L11: by UT
B12: 4 | C12: Hand Polisher | D12: Hand Polisher | E12: 2 | F12: bh | I12: 0 | J12: 0 | K12: 0 | L12: by UT
B13: 5 | C13: Blower | D13: Blower | E13: 12 | F13: bh | I13: 0 | J13: 0 | K13: 0 | L13: by UT
B14: 6 | C14: Janitor Cart | D14: Janitor Cart | E14: 12 | F14: bh | I14: 0 | J14: 0 | K14: 0 | L14: by UT
B15: 7 | C15: Air Deodorizer Glade Liquid Ocean Escape 4L | D15: Air Deodorizer Glade Liquid Ocean Escape 4L | E15: 36 | F15: bh | G15: 108 | H15: Gln | I15: =121770*107% -> 130293.9 | J15: 12 | K15: =(I15*G15)/J15 -> 1172645.1 | L15: PPI-Cakung
B16: 8 | C16: Body Bag | D16: Body Bag | E16: 60 | F16: bh | G16: 84 | H16: Pcs | I16: =132000*107% -> 141240 | J16: 12 | K16: =(I16*G16)/J16 -> 988680 | L16: PPI-Cakung
B17: 9 | C17: Botol Sprayer | D17: Botol Sprayer | E17: 60 | F17: bh | G17: 180 | H17: Pcs | I17: =49500*107% -> 52965 | J17: 12 | K17: =(I17*G17)/J17 -> 794475 | L17: PPI-Cakung
B18: 10 | C18: Bucket - Double 2X2,5L | D18: Bucket - Double 2X2,5L | E18: 12 | F18: bh | G18: 24 | H18: Set | I18: =924000*107% -> 988680 | J18: 12 | K18: =(I18*G18)/J18 -> 1977360 | L18: PPI-Cakung
B19: 11 | C19: Cady Cary | D19: Cady Cary | E19: 12 | F19: bh | G19: 24 | H19: Pcs | I19: =92906*107% -> 99409.42 | J19: 12 | K19: =(I19*G19)/J19 -> 198818.84 | L19: PPI-Cakung
B20: 12 | C20: Carpet Care Refresh 4L | D20: Carpet Care Refresh 4L | E20: 36 | F20: bh | G20: 24 | H20: Gln | I20: =246840*107% -> 264118.8 | J20: 12 | K20: =(I20*G20)/J20 -> 528237.6 | L20: PPI-Cakung
B21: 13 | C21: Carpet Care Rugbee Hdssr 4L | D21: Carpet Care Rugbee Hdssr 4L | E21: 24 | F21: bh | G21: 12 | H21: Gln | I21: =352990*107% -> 377699.3 | J21: 12 | K21: =(I21*G21)/J21 -> 377699.3 | L21: PPI-Cakung
B22: 14 | C22: Carpet Care Rugbee Shampoo 4L | D22: Carpet Care Rugbee Shampoo 4L | E22: 36 | F22: bh | G22: 144 | H22: Gln | I22: =170720*107% -> 182670.4 | J22: 12 | K22: =(I22*G22)/J22 -> 2192044.8 | L22: PPI-Cakung
B23: 15 | C23: Dust Bin 120L | D23: Dust Bin 120L | E23: 12 | F23: bh | G23: 24 | H23: Pcs | I23: =946000*107% -> 1012220 | J23: 12 | K23: =(I23*G23)/J23 -> 2024440 | L23: PPI-Cakung
B24: 16 | C24: Dustpan Kecil | D24: Dustpan Kecil | E24: 24 | F24: bh | G24: 240 | H24: Pcs | I24: =44000*107% -> 47080 | J24: 12 | K24: =(I24*G24)/J24 -> 941600 | L24: PPI-Cakung
B25: 17 | C25: Ember Biru 4L | D25: Ember Biru 6L | E25: 24 | F25: bh | G25: 120 | H25: Pcs | I25: =92700*107% -> 99189 | J25: 12 | K25: =(I25*G25)/J25 -> 991890 | L25: PPI-Cakung
B26: 18 | C26: Floor Sealer Finish New Complete 4L | D26: Floor Sealer Finish New Complete 4L | E26: 24 | F26: bh | G26: 96 | H26: Gln | I26: =340010*107% -> 363810.7 | J26: 12 | K26: =(I26*G26)/J26 -> 2910485.6 | L26: PPI-Cakung
B27: 19 | C27: Floor Squeegee | D27: Floor Squeegee | E27: 60 | F27: bh | G27: 300 | H27: Pcs | I27: =37968.7*107% -> 40626.509 | J27: 12 | K27: =(I27*G27)/J27 -> 1015662.7 | L27: PPI-Cakung
B28: 20 | C28: Floor Stripper Wax Strip 4L | D28: Floor Stripper Wax Strip 4L | E28: 24 | F28: bh | G28: 60 | H28: Gln | I28: =86881.3*107% -> 92962.991 | J28: 12 | K28: =(I28*G28)/J28 -> 464814.96 | L28: PPI-Cakung
B29: 21 | C29: Fragrance Oil Sicher Natural Lemongrass 1L | D29: Fragrance Oil Sicher Natural Lemongrass 1L | E29: 24 | F29: bh | G29: 24 | H29: Btl | I29: =769560*107% -> 823429.2 | J29: 12 | K29: =(I29*G29)/J29 -> 1646858.4 | L29: PPI-Cakung
B30: 22 | C30: Furniture Care Shine Up Premium 2L | D30: Furniture Care Shine Up Premium 2L | E30: 24 | F30: bh | G30: 240 | H30: Gln | I30: =137500*107% -> 147125 | J30: 12 | K30: =(I30*G30)/J30 -> 2942500 | L30: PPI-Cakung
B31: 23 | C31: Gayung | D31: Gayung | E31: 24 | F31: bh | G31: 12 | H31: Pcs | I31: =22000*107% -> 23540 | J31: 12 | K31: =(I31*G31)/J31 -> 23540 | L31: PPI-Cakung
B32: 24 | C32: Gel Pengharum Kloset | D32: Gel Pengharum Kloset | E32: 348 | F32: bh | G32: 4200 | H32: Pcs | I32: =9000*107% -> 9630 | J32: 12 | K32: =(I32*G32)/J32 -> 3370500 | L32: PPI-Cakung
B33: 25 | C33: Hand Soap 20L | D33: Hand Soap 20L | E33: 24 | F33: bh | G33: 60 | H33: Pail | I33: =296000*107% -> 316720 | J33: 12 | K33: =(I33*G33)/J33 -> 1583600 | L33: PPI-Cakung
B34: 26 | C34: Hand Soap 5L | D34: Hand Soap 5L | E34: 120 | F34: bh | G34: 240 | H34: Gln | I34: =92000*107% -> 98440 | J34: 12 | K34: =(I34*G34)/J34 -> 1968800 | L34: PPI-Cakung
B35: 27 | C35: Kamper Isi 5 | D35: Kamper Isi 5 | E35: 156 | F35: bh | G35: 240 | H35: Pax | I35: =28500*107% -> 30495 | J35: 12 | K35: =(I35*G35)/J35 -> 609900 | L35: PPI-Cakung
B36: 28 | C36: Kanebo | D36: Kanebo | E36: 60 | F36: bh | G36: 360 | H36: Pcs | I36: =38000*107% -> 40660 | J36: 12 | K36: =(I36*G36)/J36 -> 1219800 | L36: PPI-Cakung
B37: 29 | C37: Kape 2 Inch | D37: Kape 2 Inch | E37: 36 | F37: bh | G37: 36 | H37: Pcs | I37: =9450*107% -> 10111.5 | J37: 12 | K37: =(I37*G37)/J37 -> 30334.5 | L37: PPI-Cakung
B38: 30 | C38: Kape 4 Inch | D38: Kape 4 Inch | E38: 36 | F38: bh | G38: 36 | H38: Pcs | I38: =16600*107% -> 17762 | J38: 12 | K38: =(I38*G38)/J38 -> 53286 | L38: PPI-Cakung
B39: 31 | C39: Kemoceng | D39: Kemoceng | E39: 72 | F39: bh | G39: 120 | H39: Pcs | I39: =23000*107% -> 24610 | J39: 12 | K39: =(I39*G39)/J39 -> 246100 | L39: PPI-Cakung
B40: 32 | C40: Kop | D40: Kop | E40: 36 | F40: bh | G40: 24 | H40: Pcs | I40: =55000*107% -> 58850 | J40: 12 | K40: =(I40*G40)/J40 -> 117700 | L40: PPI-Cakung
B41: 33 | C41: Kuas 2 Inch | D41: Kuas 2 Inch | E41: 36 | F41: bh | G41: 72 | H41: Pcs | I41: =12500*107% -> 13375 | J41: 12 | K41: =(I41*G41)/J41 -> 80250 | L41: PPI-Cakung
B42: 34 | C42: Kuas 4 Inch | D42: Kuas 4 Inch | E42: 36 | F42: bh | G42: 120 | H42: Pcs | I42: =19900*107% -> 21293 | J42: 12 | K42: =(I42*G42)/J42 -> 212930 | L42: PPI-Cakung
B43: 35 | C43: Lap Microfiber Biru | D43: Lap Microfiber Biru | E43: 96 | F43: bh | G43: 600 | H43: Pcs | I43: =26013.9*107% -> 27834.873 | J43: 12 | K43: =(I43*G43)/J43 -> 1391743.7 | L43: PPI-Cakung
B44: 36 | C44: Lap Microfiber Kuning | D44: Lap Microfiber Kuning | E44: 96 | F44: bh | G44: 240 | H44: Pcs | I44: =26013.9*107% -> 27834.873 | J44: 12 | K44: =(I44*G44)/J44 -> 556697.46 | L44: PPI-Cakung
B45: 37 | C45: Lap Microfiber Merah | D45: Lap Microfiber Merah | E45: 36 | F45: bh | G45: 360 | H45: Pcs | I45: =26013.9*107% -> 27834.873 | J45: 12 | K45: =(I45*G45)/J45 -> 835046.19 | L45: PPI-Cakung
B46: 38 | C46: Lobby Duster Kain 60 Inch | D46: Lobby Duster Kain 60 Inch | E46: 60 | F46: bh | G46: 180 | H46: Pcs | I46: =83200*107% -> 89024 | J46: 12 | K46: =(I46*G46)/J46 -> 1335360 | L46: PPI-Cakung
B47: 39 | C47: Lobby Duster Kain 80 Inch | D47: Lobby Duster Kain 80 Inch | E47: 36 | F47: bh | G47: 120 | H47: Pcs | I47: 76235 | J47: 12 | K47: =(I47*G47)/J47 -> 762350 | L47: PPI-Cakung
B48: 40 | C48: Lobby Duster Set 60 Inch | D48: Lobby Duster Set 60 Inch | E48: 48 | F48: bh | G48: 36 | H48: Set | I48: =162500*107% -> 173875 | J48: 12 | K48: =(I48*G48)/J48 -> 521625 | L48: PPI-Cakung
B49: 41 | C49: Lobby Duster Set 80 Inch | D49: Lobby Duster Set 80 Inch | E49: 24 | F49: bh | G49: 24 | H49: Set | I49: =180271*107% -> 192889.97 | J49: 12 | K49: =(I49*G49)/J49 -> 385779.94 | L49: PPI-Cakung
B50: 42 | C50: Marble Crystalization Marble Powder | D50: Marble Crystalization Marble Powder | E50: 168 | F50: bh | G50: 420 | H50: Set | I50: =226700*107% -> 242569 | J50: 12 | K50: =(I50*G50)/J50 -> 8489915 | L50: PPI-Cakung
B51: 43 | C51: Mop Kain Biru | D51: Mop Kain Biru | E51: 48 | F51: bh | G51: 240 | H51: Pcs | I51: =46487.2*107% -> 49741.304 | J51: 12 | K51: =(I51*G51)/J51 -> 994826.08 | L51: PPI-Cakung
B52: 44 | C52: Mop Kain Putih | D52: Mop Kain Putih | E52: 60 | F52: bh | G52: 360 | H52: Pcs | I52: =61922.4*107% -> 66256.968 | J52: 12 | K52: =(I52*G52)/J52 -> 1987709 | L52: PPI-Cakung
B53: 45 | C53: Mop Set | D53: Mop Set | E53: 24 | F53: bh | G53: 60 | H53: Set | I53: =117749.2*107% -> 125991.64 | J53: 12 | K53: =(I53*G53)/J53 -> 629958.22 | L53: PPI-Cakung
B54: 46 | C54: Neutral Cleaner Expose 4L | D54: Neutral Cleaner Expose 4L | E54: 48 | F54: bh | G54: 120 | H54: Gln | I54: =151200*107% -> 161784 | J54: 12 | K54: =(I54*G54)/J54 -> 1617840 | L54: PPI-Cakung
B55: 47 | C55: Neutral Cleaner Marble Klin 4L | D55: Neutral Cleaner Marble Klin 4L | E55: 48 | F55: bh | G55: 180 | H55: Gln | I55: =145440*107% -> 155620.8 | J55: 12 | K55: =(I55*G55)/J55 -> 2334312 | L55: PPI-Cakung
B56: 48 | C56: Nyloon Broom | D56: Nyloon Broom | E56: 36 | F56: bh | G56: 240 | H56: Pcs | I56: =37400*107% -> 40018 | J56: 12 | K56: =(I56*G56)/J56 -> 800360 | L56: PPI-Cakung
B57: 49 | C57: Obat Nyamuk Spray Baygon 600Ml | D57: Obat Nyamuk Spray Baygon 600Ml | E57: 60 | F57: bh | I57: 0 | J57: 0 | K57: 0 | L57: by UT
B58: 50 | C58: Obat Nyamuk Spray Hit 600Ml | D58: Obat Nyamuk Spray Hit 600Ml | E58: 60 | F58: bh | I58: 0 | J58: 0 | K58: 0 | L58: by UT
B59: 51 | C59: Obat Rayap Premise | D59: Obat Rayap Premise | E59: 60 | F59: bh | I59: 0 | J59: 0 | K59: 0 | L59: by UT
B60: 52 | C60: Pad Coklat 17 Inch | D60: Pad Coklat 17 Inch | E60: 24 | F60: bh | G60: 84 | H60: Pcs | I60: =138520*107% -> 148216.4 | J60: 12 | K60: =(I60*G60)/J60 -> 1037514.8 | L60: PPI-Cakung
B61: 53 | C61: Pad Merah 17 Inch | D61: Pad Merah 17 Inch | E61: 96 | F61: bh | G61: 480 | H61: Pcs | I61: =138520*107% -> 148216.4 | J61: 12 | K61: =(I61*G61)/J61 -> 5928656 | L61: PPI-Cakung
B62: 54 | C62: Pad Merah 20 Inch | D62: Pad Merah 20 Inch | E62: 36 | F62: bh | G62: 12 | H62: Pcs | I62: =138520*107% -> 148216.4 | J62: 12 | K62: =(I62*G62)/J62 -> 148216.4 | L62: PPI-Cakung
B63: 55 | C63: Pad Putih 17 Inch | D63: Pad Putih 17 Inch | E63: 72 | F63: bh | G63: 360 | H63: Pcs | I63: =138520*107% -> 148216.4 | J63: 12 | K63: =(I63*G63)/J63 -> 4446492 | L63: PPI-Cakung
B64: 56 | C64: Pembersih Kaca Glance Glass Cleaner 4L | D64: Pembersih Kaca Glance Glass Cleaner 4L | E64: 84 | F64: bh | G64: 300 | H64: Gln | I64: =66720*107% -> 71390.4 | J64: 12 | K64: =(I64*G64)/J64 -> 1784760 | L64: PPI-Cakung
B65: 57 | C65: Pembersih Kaca Strip Powder | D65: Pembersih Kaca Strip Powder | E65: 84 | F65: bh | G65: 120 | H65: Btl | I65: =32500*107% -> 34775 | J65: 12 | K65: =(I65*G65)/J65 -> 347750 | L65: PPI-Cakung
B66: 58 | C66: Pembersih Lantai Brite Plus 4L | D66: Pembersih Lantai Brite Plus 4L | E66: 84 | F66: bh | G66: 300 | H66: Gln | I66: =88700*107% -> 94909 | J66: 12 | K66: =(I66*G66)/J66 -> 2372725 | L66: PPI-Cakung
B67: 59 | C67: Pembersih Lantai Forward 4L | D67: Pembersih Lantai Forward 4L | E67: 72 | F67: bh | G67: 360 | H67: Gln | I67: =122800*107% -> 131396 | J67: 12 | K67: =(I67*G67)/J67 -> 3941880 | L67: PPI-Cakung
B68: 60 | C68: Pembersih Lantai Karbol 4L | D68: Pembersih Lantai Karbol 4L | E68: 36 | F68: bh | G68: 120 | H68: Gln | I68: =68400*107% -> 73188 | J68: 12 | K68: =(I68*G68)/J68 -> 731880 | L68: PPI-Cakung
B69: 61 | C69: Pembersih Noda Sns 500Ml | D69: Pembersih Noda Sns 500Ml | E69: 24 | F69: bh | G69: 24 | H69: Btl | I69: =114000*107% -> 121980 | J69: 12 | K69: =(I69*G69)/J69 -> 243960 | L69: PPI-Cakung
B70: 62 | C70: Pembersih Toilet Go Getter 4L | D70: Pembersih Toilet Go Getter 4L | E70: 84 | F70: bh | G70: 360 | H70: Gln | I70: =83909.2*107% -> 89782.844 | J70: 12 | K70: =(I70*G70)/J70 -> 2693485.3 | L70: PPI-Cakung
B71: 63 | C71: Pengkilap Lantai Hi Gloss | D71: Pengkilap Lantai Hi Gloss | E71: 60 | F71: bh | G71: 480 | H71: Pcs | I71: =76720*107% -> 82090.4 | J71: 12 | K71: =(I71*G71)/J71 -> 3283616 | L71: PPI-Cakung
B72: 64 | C72: Plastik Sampah Hijau 90X120 | D72: Plastik Sampah Hijau 90X120 | E72: 312 | F72: bh | G72: 3000 | H72: Pax | I72: =41840*107% -> 44768.8 | J72: 12 | K72: =(I72*G72)/J72 -> 11192200 | L72: PPI-Cakung
B73: 65 | C73: Plastik Sampah Hitam 60X100 | D73: Plastik Sampah Hitam 60X100 | E73: 36 | F73: bh | G73: 1200 | H73: Pax | I73: =20160*107% -> 21571.2 | J73: 12 | K73: =(I73*G73)/J73 -> 2157120 | L73: PPI-Cakung
B74: 66 | C74: Plastik Sampah Hitam 90X120 | D74: Plastik Sampah Hitam 90X120 | E74: 168 | F74: bh | G74: 1200 | H74: Pax | I74: =20160*107% -> 21571.2 | J74: 12 | K74: =(I74*G74)/J74 -> 2157120 | L74: PPI-Cakung
B75: 67 | C75: Plastik Sampah Kuning 60X100 | D75: Plastik Sampah Kuning 60X100 | E75: 96 | F75: bh | G75: 120 | H75: Pax | I75: =43200*107% -> 46224 | J75: 12 | K75: =(I75*G75)/J75 -> 462240 | L75: PPI-Cakung
B76: 68 | C76: Rugball | D76: Rugball | E76: 24 | F76: bh | G76: 60 | H76: Pcs | I76: =88000*107% -> 94160 | J76: 12 | K76: =(I76*G76)/J76 -> 470800 | L76: PPI-Cakung
B77: 69 | C77: Sabun Cuci Rinso 770Gr | D77: Sabun Cuci Rinso 770Gr | E77: 60 | F77: bh | G77: 180 | H77: Pcs | I77: =45000*107% -> 48150 | J77: 12 | K77: =(I77*G77)/J77 -> 722250 | L77: PPI-Cakung
B78: 70 | C78: Sabun Krim Wings 900Gr | D78: Sabun Krim Wings 900Gr | E78: 132 | F78: bh | G78: 180 | H78: Pcs | I78: =29000*107% -> 31030 | J78: 12 | K78: =(I78*G78)/J78 -> 465450 | L78: PPI-Cakung
B79: 71 | C79: Sanitation Break Up 4L | D79: Sanitation Break Up 4L | E79: 96 | F79: bh | G79: 240 | H79: Gln | I79: =188297.6*107% -> 201478.43 | J79: 12 | K79: =(I79*G79)/J79 -> 4029568.6 | L79: PPI-Cakung
B80: 72 | C80: Sapu Lidi Tanpa Gagang | D80: Sapu Lidi Tanpa Gagang | E80: 36 | F80: bh | G80: 24 | H80: Pcs | I80: =7200*107% -> 7704 | J80: 12 | K80: =(I80*G80)/J80 -> 15408 | L80: PPI-Cakung
B81: 73 | C81: Sarung Tangan Kain | D81: Sarung Tangan Kain | E81: 60 | F81: bh | G81: 120 | H81: Psg | I81: =12800*107% -> 13696 | J81: 12 | K81: =(I81*G81)/J81 -> 136960 | L81: PPI-Cakung
B82: 74 | C82: Sarung Tangan Karet | D82: Sarung Tangan Karet | E82: 1464 | F82: bh | G82: 960 | H82: Psg | I82: =26270.4*107% -> 28109.328 | J82: 12 | K82: =(I82*G82)/J82 -> 2248746.2 | L82: PPI-Cakung
B83: 75 | C83: Sikat Tangan Plastik | D83: Sikat Tangan Plastik | E83: 72 | F83: bh | G83: 36 | H83: Pcs | I83: =21000*107% -> 22470 | J83: 12 | K83: =(I83*G83)/J83 -> 67410 | L83: PPI-Cakung
B84: 76 | C84: Sikat Tangkai Panjang | D84: Sikat Tangkai Panjang | E84: 48 | F84: bh | G84: 120 | H84: Pcs | I84: =56325.2*107% -> 60267.964 | J84: 12 | K84: =(I84*G84)/J84 -> 602679.64 | L84: PPI-Cakung
B85: 77 | C85: Speciality Cleaner Conq R Dust 4L | D85: Speciality Cleaner Conq R Dust 4L | E85: 36 | F85: bh | G85: 60 | H85: Gln | I85: =272525*107% -> 291601.75 | J85: 12 | K85: =(I85*G85)/J85 -> 1458008.8 | L85: PPI-Cakung
B86: 78 | C86: Speciality Cleaner Glo Metal Polish 2L | D86: Speciality Cleaner Glo Metal Polish 2L | E86: 24 | F86: bh | G86: 60 | H86: Gln | I86: =221030*107% -> 236502.1 | J86: 12 | K86: =(I86*G86)/J86 -> 1182510.5 | L86: PPI-Cakung
B87: 79 | C87: Steel Woll | D87: Steel Woll | E87: 60 | F87: bh | G87: 420 | H87: Pcs | I87: =48080*107% -> 51445.6 | J87: 12 | K87: =(I87*G87)/J87 -> 1800596 | L87: PPI-Cakung
B88: 80 | C88: Telescopic Pole 9M | D88: Telescopic Pole 9M | E88: 24 | F88: bh | G88: 12 | H88: Pcs | I88: =506757.6*107% -> 542230.63 | J88: 12 | K88: =(I88*G88)/J88 -> 542230.63 | L88: PPI-Cakung
B89: 81 | C89: Tisu Meja Paseo | D89: Tisu Meja Paseo | E89: 60 | F89: bh | G89: 60 | H89: Pcs | I89: =13500*107% -> 14445 | J89: 12 | K89: =(I89*G89)/J89 -> 72225 | L89: PPI-Cakung | N89: Calmic
B90: 82 | C90: Toilet Bowl Brush | D90: Toilet Bowl Brush | E90: 60 | F90: bh | G90: 240 | H90: Pcs | I90: =19900*107% -> 21293 | J90: 12 | K90: =(I90*G90)/J90 -> 425860 | L90: PPI-Cakung | N90: 35000000
B91: 83 | C91: Tube Brush | D91: Tube Brush | E91: 72 | F91: bh | G91: 12 | H91: Pcs | I91: =172000*107% -> 184040 | J91: 12 | K91: =(I91*G91)/J91 -> 184040 | L91: PPI-Cakung | N91: 389583
B92: 84 | C92: Urinal Screen | D92: Urinal Screen | E92: 1344 | F92: bh | G92: 1500 | H92: Pcs | I92: =48510*107% -> 51905.7 | J92: 12 | K92: =(I92*G92)/J92 -> 6488212.5 | L92: PPI-Cakung | N92: 618750
B93: 85 | C93: Warning Sign Wet Floor | D93: Warning Sign Wet Floor | E93: 24 | F93: bh | G93: 36 | H93: Pcs | I93: =115405.6*107% -> 123483.99 | J93: 12 | K93: =(I93*G93)/J93 -> 370451.98 | L93: PPI-Cakung | N93: 4125000
B94: 86 | C94: Window Squeegee 35 Inch | D94: Window Squeegee 35 Inch | E94: 84 | F94: bh | G94: 240 | H94: Pcs | I94: =54000*107% -> 57780 | J94: 12 | K94: =(I94*G94)/J94 -> 1155600 | L94: PPI-Cakung | N94: 412500
B95: 87 | C95: Window Washer 35 Inch | D95: Window Washer 35 Inch | E95: 72 | F95: bh | G95: 240 | H95: Pcs | I95: =46554.3*107% -> 49813.101 | J95: 12 | K95: =(I95*G95)/J95 -> 996262.02 | L95: PPI-Cakung | N95: 201667
B96: 88 | C96: Pengharum Ruangan Calmic, Ecocare & Scenting | D96: Pengharum Ruangan Calmic, Ecocare & Scenting | E96: 30 | F96: titik | G96: 1 | H96: Ls | I96: 660000000 | J96: 12 | K96: =(I96*G96)/J96 -> 55000000 | L96: PPI-Cakung | N96: 389583
B97: 89 | D97: Pembersih Kaca Glance Glass Cleaner 4L | G97: 36 | H97: Gln | I97: =66720*107% -> 71390.4 | J97: 12 | K97: =(I97*G97)/J97 -> 214171.2 | L97: SKP & Jababeka | N97: =SUM(N90:N96) -> 41137083 | O97: =K96-N97 -> 13862917
B98: 90 | D98: Pembersih Kaca Strip Powder | G98: 24 | H98: Btl | I98: =32500*107% -> 34775 | J98: 12 | K98: =(I98*G98)/J98 -> 69550 | L98: SKP & Jababeka
B99: 91 | D99: Pembersih Lantai Brite Plus 4L | G99: 48 | H99: Gln | I99: =88700*107% -> 94909 | J99: 12 | K99: =(I99*G99)/J99 -> 379636 | L99: SKP & Jababeka
B100: 92 | D100: Pembersih Lantai Forward 4L | G100: 48 | H100: Gln | I100: =122800*107% -> 131396 | J100: 12 | K100: =(I100*G100)/J100 -> 525584 | L100: SKP & Jababeka
B101: 93 | D101: Pembersih Toilet Go Getter 4L | G101: 48 | H101: Gln | I101: =83909.2*107% -> 89782.844 | J101: 12 | K101: =(I101*G101)/J101 -> 359131.38 | L101: SKP & Jababeka
B102: 94 | D102: Urinal Screen | G102: 180 | H102: Pcs | I102: =48510*107% -> 51905.7 | J102: 12 | K102: =(I102*G102)/J102 -> 778585.5 | L102: SKP & Jababeka
B103: 95 | D103: Kamper Isi 5 | G103: 84 | H103: Pax | I103: =28500*107% -> 30495 | J103: 12 | K103: =(I103*G103)/J103 -> 213465 | L103: SKP & Jababeka
B104: 96 | D104: Hand Soap 5L | G104: 48 | H104: Gln | I104: =92000*107% -> 98440 | J104: 12 | K104: =(I104*G104)/J104 -> 393760 | L104: SKP & Jababeka
...

Sheet SERTIFIKASI
A1: SERTIFIKASI SERVCES
A3: Position | B3: Scope | C3: Jenis Sertifikasi | D3: Biaya Sertifikasi | E3: Masa Berlaku | F3: Biaya/ Bulan
A4: Koordinator | B4: Cleaning Service & Quality Control | C4: Sertifikasi Cleaning Service (BNSP) | D4: 3000000 | E4: 3 Tahun | F4: =D4/36 -> 83333.333
A5: Supervisor | B5: Cleaning Service | C5: Sertifikasi Cleaning Service (BNSP) | D5: 3000000 | E5: 3 Tahun | F5: =D5/36 -> 83333.333
A6: Crew | B6: Cleaning Service | C6: Sertifikasi Cleaning Service (BNSP) | D6: 3000000 | E6: 3 Tahun | F6: =D6/36 -> 83333.333
A7: Crew | B7: Pest Control | C7: Sertifikasi Penanganan Satwa Liar Umum | D7: 3500000 | E7: 3 Tahun | F7: =D7/36 -> 97222.222
A8: Supervisor | B8: Gondola | C8: Sertifikasi IRATA (Level 2) | D8: 9000000 | E8: 3 Tahun | F8: =D8/36 -> 250000
C9: Operator Gondola (Angkat-Angkut) | D9: 4500000 | E9: 3 Tahun | F9: =D9/36 -> 125000
A10: Crew | B10: Gondola | C10: Sertifikasi IRATA (Level 1) | D10: 5500000 | E10: 3 Tahun | F10: =D10/36 -> 152777.78
C11: Operator Gondola (Angkat-Angkut) | D11: 4500000 | E11: 3 Tahun | F11: =D11/36 -> 125000

Sheet LIST MP
B5: Lampiran 2
B6: No. | C6: ='[1]Covering Letter '!D5 -> CS/0066/2025
B9: TENAGA KERJA SERVICES TAHUN 2025
B10: NAMA | E10: : PT MITRA BAKTI UT
B11: AREA PELAYANAN | E11: : PT UNITED TRACTORS TBK
B13: NO | C13: NAMA MANPOWER | D13: POSISI | E13: GENDER | F13: LOKASI KERJA | G13: PIC SUPERVISOR
B14: 1 | C14: Doni | D14: Chief SPV Housekeeping | E14: Pria | F14: PPI- Cakung
B15: 2 | C15: Wisnu Pratama | D15: Chief SPV Housekeeping | E15: Pria | F15: PPI- Cakung
B16: 3 | C16: Juhari | D16: Supervisor Kebersihan | E16: Pria | F16: Tower UTNB lantai 2 - Roof | G16: Doni
B17: 4 | C17: Cuhendi | D17: Supervisor Kebersihan | E17: Pria | F17: All Ground (Tower & Wing) & Publik Area Wing | G17: Doni
B18: 5 | C18: Andri | D18: Supervisor Kebersihan | E18: Pria | F18: Ballroom, Canteen, dan All Parkiran UTNB | G18: Doni
B19: 6 | C19: Budi Amalwan | D19: Supervisor Kebersihan | E19: Pria | F19: LC dan Publik Area HO B | G19: Doni
B20: 7 | C20: Soecipto Bhakti P | D20: Supervisor Kebersihan & Cleaning Outdoor | E20: Pria | F20: Masjid & Parkiran UTS | G20: Doni
B21: 8 | C21: Umbrus | D21: Supervisor Gardener | E21: Pria | F21: PPI Cakung - Gardener | G21: Doni
B22: 9 | C22: Maskur | D22: Supervisor Gondola | E22: Pria | F22: UTNB & WING | G22: Doni
B23: 10 | C23: Sulaiman | D23: Cleaning | E23: Pria | F23: Tower UTNB Lantai 9 | G23: Juhari
B24: 11 | C24: Desi Wulandari | D24: Cleaning | E24: Wanita | F24: Tower UTNB Lantai 9 | G24: Juhari
B25: 12 | C25: Dwi Hariwibowo | D25: Cleaning | E25: Pria | F25: Tower UTNB Lantai 9 | G25: Juhari
B26: 13 | C26: Agus Adi Subagya | D26: Cleaning | E26: Pria | F26: Tower UTNB Lantai 8 | G26: Juhari
B27: 14 | C27: Agung Ramdhan | D27: Cleaning | E27: Pria | F27: Tower UTNB Lantai 8 | G27: Juhari
... B49: 36 | C49: Rizky Septiawan | D49: Cleaning | E49: Pria | F49: Wing Public Area (Lantai Ground - Lantai 6) | G49: Cuhendi
B50: 37 | C50: Intan Wijayanti | D50: Cleaning | E50: Wanita | G50: Cuhendi
B51: 38 | C51: Arief Maulana | D51: Cleaning | E51: Pria | F51: Command Center | G51: Cuhendi
B52: 39 | C52: Yuli Setiawati | D52: Cleaning | E52: Wanita | F52: UT Call | G52: Cuhendi
B53: 40 | C53: Kamaludin | D53: Cleaning | E53: Pria | F53: Mushola UTNB Pria & Loker Security | G53: Cuhendi
B54: 41 | C54: Iskiyah | D54: Cleaning | E54: Wanita | F54: Mushola UTNB Wanita & Loker Security | G54: Cuhendi
B55: 42 | C55: Deni Purwanto | D55: Cleaning | E55: Pria | F55: Parkiran Vip & Utility Room | G55: Cuhendi
B56: 43 | C56: Ferdy | D56: Cleaning | E56: Pria | F56: Parkiran Vip & Utility Room | G56: Cuhendi
B57: 44 | C57: Ubai Achbari | D57: Cleaning | E57: Pria | F57: Staf Security & Pos A | G57: Cuhendi
B58: 45 | C58: Ari Subechi | D58: Cleaning | E58: Pria | F58: Taman Innercourt | G58: Andri
B59: 46 | C59: Andrianto | D59: Cleaning | E59: Pria | F59: Parkiran Mobil P & P1 | G59: Andri
B60: 47 | C60: Makmur A | D60: Cleaning | E60: Pria | F60: Parkiran Mobil P2 & P3 | G60: Andri
B61: 48 | C61: M. Rais | D61: Cleaning | E61: Pria | F61: Parkiran Mobil P4 | G61: Andri
B62: 49 | C62: M. Arif Faizi | D62: Cleaning | E62: Pria | F62: Parkiran Motor Lantai 2 | G62: Andri
... B167: 154 | C167: Kamalludin | D167: Pest Control | E167: Pria | F167: UT PPI-Cakung | G167: Umbrus
